[
  {
    "id": "0580-2018March-Paper42-Q01",
    "paper": "2018March-Paper42",
    "qnum": 1,
    "marks": 10,
    "topics": [
      "Number"
    ],
    "s": "1.13",
    "d": 2,
    "cat": "number",
    "topic": "Electronic calculators",
    "qtype": "multi-part problem solving with percentages, money, and bounds",
    "g": "mixed",
    "src": "0580/42/M/18 Q01",
    "year": 2018,
    "session": "March",
    "tex": "(a) A shop sells dress fabric for \\$2.97 per metre.\n\\newline\n\n(i) (b) A customer buys 9 metres of this fabric.\n\\newline\n\nCalculate the change he receives from \\$50.\n\\newline\n\n\\$ \n\n(c) The selling price of \\$2.97 per metre is an increase of 8\\% on the cost price.\n\\newline\n\nCalculate the cost price.\n\\newline\n\n\\$  per metre\n\n(d) A dressmaker charges \\$35 or 2300 rupees to make a dress.\n\\newline\n\nCalculate the difference in price when the exchange rate is 1 rupee = \\$0.0153.\n\\newline\nGive your answer in rupees.\n\\newline\n\n rupees\n\n(e) The dressmaker measures a length of fabric as 600 m, correct to the nearest 5 metres.\n\\newline\nHe cuts this into dress lengths of 9 m, correct to the nearest metre.\n\\newline\n\nCalculate the largest number of complete dress lengths he could cut.\n\\newline\n",
    "parts": [
      {
        "label": "(a)",
        "content": [
          {
            "type": "text",
            "content": "A shop sells dress fabric for \\$2.97 per metre.\n\\newline\n"
          }
        ],
        "subparts": [
          {
            "label": "(i)",
            "marks": 2,
            "content": [
              {
                "type": "text",
                "content": "A customer buys 9 metres of this fabric.\n\\newline\n\nCalculate the change he receives from \\$50.\n\\newline\n\n\\$ \\AnswerLine[][]"
              }
            ]
          },
          {
            "label": "(ii)",
            "marks": 3,
            "content": [
              {
                "type": "text",
                "content": "The selling price of \\$2.97 per metre is an increase of 8\\% on the cost price.\n\\newline\n\nCalculate the cost price.\n\\newline\n\n\\$ \\AnswerLine[][] per metre"
              }
            ]
          }
        ],
        "_subpartCmd": "item"
      },
      {
        "label": "(b)",
        "marks": 2,
        "content": [
          {
            "type": "text",
            "content": "A dressmaker charges \\$35 or 2300 rupees to make a dress.\n\\newline\n\nCalculate the difference in price when the exchange rate is 1 rupee = \\$0.0153.\n\\newline\nGive your answer in rupees.\n\\newline\n"
          }
        ],
        "answer": {
          "type": "number"
        }
      },
      {
        "label": "(c)",
        "marks": 3,
        "content": [
          {
            "type": "text",
            "content": "The dressmaker measures a length of fabric as 600 m, correct to the nearest 5 metres.\n\\newline\nHe cuts this into dress lengths of 9 m, correct to the nearest metre.\n\\newline\n\nCalculate the largest number of complete dress lengths he could cut.\n\\newline\n"
          }
        ],
        "answer": {
          "type": "number"
        }
      }
    ],
    "hasFigure": false,
    "cognitive": "apply",
    "cmd": "complete",
    "stem": [],
    "_rawBody": "\\begin{parts}\n\\item A shop sells dress fabric for \\$2.97 per metre.\n\n\\begin{subparts}\n\\item A customer buys 9 metres of this fabric.\n\nCalculate the change he receives from \\$50.\n\n\\$ \\AnswerLine[][]\n\n\\Marks{2}\n\n\\item The selling price of \\$2.97 per metre is an increase of 8\\% on the cost price.\n\nCalculate the cost price.\n\n\\$ \\AnswerLine[][] per metre\n\n\\Marks{3}\n\n\\end{subparts}\n\n\\item A dressmaker charges \\$35 or 2300 rupees to make a dress.\n\nCalculate the difference in price when the exchange rate is 1 rupee = \\$0.0153.\nGive your answer in rupees.\n\n\\AnswerLine[][] rupees\n\n\\Marks{2}\n\n\\item The dressmaker measures a length of fabric as 600 m, correct to the nearest 5 metres.\nHe cuts this into dress lengths of 9 m, correct to the nearest metre.\n\nCalculate the largest number of complete dress lengths he could cut.\n\n\\AnswerLine[][]\n\n\\Marks{3}\n\n\\end{parts}",
    "_compactParts": true
  },
  {
    "id": "0580-2018March-Paper42-Q02",
    "paper": "2018March-Paper42",
    "qnum": 2,
    "marks": 9,
    "topics": [
      "Geometry",
      "Mensuration"
    ],
    "s": "4.1",
    "d": 2,
    "cat": "geometry",
    "topic": "Angles",
    "qtype": "geometrical terms",
    "g": "mixed",
    "src": "0580/42/M/18 Q02",
    "year": 2018,
    "session": "March",
    "tex": "The vertices of a square ABCD lie on the circumference of a circle, radius 8 cm.\n\\newline\n\n\\begin{InsertScreenShot}\n    [Diagram]\n}\n    }\n\\end{InsertScreenShot}\n\n(a) Calculate the area of the square.\n\\newline\n\n(b) Calculate the area of the shaded segment.\n\\newline\n\n(c) Calculate the perimeter of the shaded segment.\n\\newline\n",
    "parts": [
      {
        "label": "(a)",
        "marks": 2,
        "content": [
          {
            "type": "text",
            "content": "Calculate the area of the square.\n\\newline\n"
          }
        ],
        "answer": {
          "type": "number",
          "suffix": "cm$^2$"
        }
      },
      {
        "label": "(b)",
        "marks": 3,
        "content": [
          {
            "type": "text",
            "content": "Calculate the area of the shaded segment.\n\\newline\n"
          }
        ],
        "answer": {
          "type": "number",
          "suffix": "cm$^2$"
        }
      },
      {
        "label": "(c)",
        "marks": 4,
        "content": [
          {
            "type": "text",
            "content": "Calculate the perimeter of the shaded segment.\n\\newline\n"
          }
        ],
        "answer": {
          "type": "number",
          "suffix": "cm"
        }
      }
    ],
    "hasFigure": true,
    "cognitive": "apply",
    "cmd": "calculate",
    "stem": [
      {
        "type": "text",
        "content": "The vertices of a square ABCD lie on the circumference of a circle, radius 8 cm.\n\\newline\n"
      },
      {
        "type": "figure",
        "src": "https://git25math.github.io/25maths-cie0580-figures/2018March/Paper42/Q02/Q02.png"
      },
      {
        "type": "figure",
        "src": "https://git25math.github.io/25maths-cie0580-figures/2018March/Paper42/Q02/Q02-CircleSquare.png"
      },
      {
        "type": "table",
        "content": "\\begin{InsertScreenShot}\n    \\IfFileExists{\\currfiledir Figures/Q02-SquareCircle.png}{\n        \\relincludegraphics{Figures/Q02-SquareCircle.png}\n    }{\n        \\fbox{\\parbox{0.4\\textwidth}{\\centering\\vspace{2cm}[Q02-SquareCircle.png]\\vspace{2cm}}}\n    }\n\\end{InsertScreenShot}"
      }
    ],
    "_rawBody": "The vertices of a square ABCD lie on the circumference of a circle, radius 8 cm.\n\n\\begin{InsertScreenShot}\n    \\IfFileExists{\\currfiledir Figures/Q02-SquareCircle.png}{\n        \\relincludegraphics{Figures/Q02-SquareCircle.png}\n    }{\n        \\fbox{\\parbox{0.4\\textwidth}{\\centering\\vspace{2cm}[Q02-SquareCircle.png]\\vspace{2cm}}}\n    }\n\\end{InsertScreenShot}\n\n\\begin{parts}\n\\item Calculate the area of the square.\n\n\\AnswerLine[][cm$^2$]\n\n\\Marks{2}\n\n\\item Calculate the area of the shaded segment.\n\n\\AnswerLine[][cm$^2$]\n\n\\Marks{3}\n\n\\item Calculate the perimeter of the shaded segment.\n\n\\AnswerLine[][cm]\n\n\\Marks{4}\n\n\\end{parts}",
    "_compactParts": true,
    "figureUrls": [
      "https://git25math.github.io/25maths-cie0580-figures/2018March/Paper42/Q02/Q02-CircleSquare.png",
      "https://git25math.github.io/25maths-cie0580-figures/2018March/Paper42/Q02/Q02.png"
    ]
  },
  {
    "id": "0580-2018March-Paper42-Q03",
    "paper": "2018March-Paper42",
    "qnum": 3,
    "marks": 15,
    "topics": [
      "Algebra and graphs"
    ],
    "s": "2.10",
    "d": 2,
    "cat": "algebra",
    "topic": "Graphs of functions",
    "qtype": "graphing functions, solving equations and inequalities graphically",
    "g": "function",
    "src": "0580/42/M/18 Q03",
    "year": 2018,
    "session": "March",
    "tex": "The table shows some values for $y = 2x + \\dfrac{1}{x} - 3$ for $0.125 \\leq x \\leq 3$.\n\\newline\n\n\\begin{InsertScreenShot}\n    [Diagram]\n}\n    }\n\\end{InsertScreenShot}\n\n(a) Complete the table.\n\\newline\n\n(b) On the grid, draw the graph of $y = 2x + \\dfrac{1}{x} - 3$ for $0.125 \\leq x \\leq 3$.\n\\newline\n\n(c) Use your graph to solve $2x + \\dfrac{1}{x} - 3 \\geq 2$.\n\\newline\n\n(d) The equation $\\dfrac{1}{x} = 7 - 3x$ can be solved using your graph in part (b) and a straight line.\n\\newline\n\n(i) (e) Write down the equation of this straight line.\n\\newline\n\n(f) Draw this straight line and solve the equation $\\dfrac{1}{x} = 7 - 3x$.\n\\newline\n\n or",
    "parts": [
      {
        "label": "(a)",
        "marks": 3,
        "content": [
          {
            "type": "text",
            "content": "Complete the table.\n\\newline\n"
          }
        ]
      },
      {
        "label": "(b)",
        "marks": 4,
        "content": [
          {
            "type": "figure",
            "src": "https://git25math.github.io/25maths-cie0580-figures/2018March/Paper42/Q03/Q03b.png"
          },
          {
            "type": "text",
            "content": "On the grid, draw the graph of $y = 2x + \\dfrac{1}{x} - 3$ for $0.125 \\leq x \\leq 3$.\n\\newline\n"
          }
        ]
      },
      {
        "label": "(c)",
        "marks": 3,
        "content": [
          {
            "type": "text",
            "content": "Use your graph to solve $2x + \\dfrac{1}{x} - 3 \\geq 2$.\n\\newline\n"
          }
        ],
        "answer": {
          "type": "multiline",
          "lines": 2,
          "template": "____\\n____",
          "lineSep": "blank"
        }
      },
      {
        "label": "(d)",
        "content": [
          {
            "type": "text",
            "content": "The equation $\\dfrac{1}{x} = 7 - 3x$ can be solved using your graph in part (b) and a straight line.\n\\newline\n"
          }
        ],
        "subparts": [
          {
            "label": "(i)",
            "marks": 2,
            "content": [
              {
                "type": "text",
                "content": "Write down the equation of this straight line.\n\\newline\n"
              }
            ],
            "answer": {
              "type": "number"
            }
          },
          {
            "label": "(ii)",
            "marks": 3,
            "content": [
              {
                "type": "text",
                "content": "Draw this straight line and solve the equation $\\dfrac{1}{x} = 7 - 3x$.\n\\newline\n"
              }
            ],
            "answer": {
              "type": "multiline",
              "lines": 2,
              "template": "$x = $ ____\\n$x = $ ____",
              "lineSep": "blank"
            }
          }
        ],
        "_subpartCmd": "item"
      }
    ],
    "hasFigure": true,
    "cognitive": "apply",
    "cmd": "draw",
    "stem": [
      {
        "type": "text",
        "content": "The table shows some values for $y = 2x + \\dfrac{1}{x} - 3$ for $0.125 \\leq x \\leq 3$.\n\\newline\n"
      },
      {
        "type": "figure",
        "src": "https://git25math.github.io/25maths-cie0580-figures/2018March/Paper42/Q03/Q03.png"
      },
      {
        "type": "figure",
        "src": "https://git25math.github.io/25maths-cie0580-figures/2018March/Paper42/Q03/Q03-GraphGrid.png"
      },
      {
        "type": "table",
        "content": "\\begin{InsertScreenShot}\n    \\IfFileExists{\\currfiledir Figures/Q03-TableGraph.png}{\n        \\relincludegraphics{Figures/Q03-TableGraph.png}\n    }{\n        \\fbox{\\parbox{0.8\\textwidth}{\\centering\\vspace{2cm}[Q03-TableGraph.png]\\vspace{2cm}}}\n    }\n\\end{InsertScreenShot}"
      }
    ],
    "_rawBody": "The table shows some values for $y = 2x + \\dfrac{1}{x} - 3$ for $0.125 \\leq x \\leq 3$.\n\n\\begin{InsertScreenShot}\n    \\IfFileExists{\\currfiledir Figures/Q03-TableGraph.png}{\n        \\relincludegraphics{Figures/Q03-TableGraph.png}\n    }{\n        \\fbox{\\parbox{0.8\\textwidth}{\\centering\\vspace{2cm}[Q03-TableGraph.png]\\vspace{2cm}}}\n    }\n\\end{InsertScreenShot}\n\n\\begin{parts}\n\\item Complete the table.\n\n\\Marks{3}\n\n\\item On the grid, draw the graph of $y = 2x + \\dfrac{1}{x} - 3$ for $0.125 \\leq x \\leq 3$.\n\n\\Marks{4}\n\n\\item Use your graph to solve $2x + \\dfrac{1}{x} - 3 \\geq 2$.\n\n\\AnswerLine[][]\n\n\\AnswerLine[][]\n\n\\Marks{3}\n\n\\item The equation $\\dfrac{1}{x} = 7 - 3x$ can be solved using your graph in part (b) and a straight line.\n\n\\begin{subparts}\n\\item Write down the equation of this straight line.\n\n\\AnswerLine[][]\n\n\\Marks{2}\n\n\\item Draw this straight line and solve the equation $\\dfrac{1}{x} = 7 - 3x$.\n\n\\AnswerLine[$x = $][] or \\AnswerLine[$x = $][]\n\n\\Marks{3}\n\n\\end{subparts}\n\n\\end{parts}",
    "_compactParts": true,
    "figureUrls": [
      "https://git25math.github.io/25maths-cie0580-figures/2018March/Paper42/Q03/Q03-GraphGrid.png",
      "https://git25math.github.io/25maths-cie0580-figures/2018March/Paper42/Q03/Q03-XYValueTable.png",
      "https://git25math.github.io/25maths-cie0580-figures/2018March/Paper42/Q03/Q03.png",
      "https://git25math.github.io/25maths-cie0580-figures/2018March/Paper42/Q03/Q03b.png"
    ]
  },
  {
    "id": "0580-2018March-Paper42-Q04",
    "paper": "2018March-Paper42",
    "qnum": 4,
    "marks": 12,
    "topics": [
      "Algebra and graphs"
    ],
    "s": "2.3",
    "d": 2,
    "cat": "algebra",
    "topic": "Indices",
    "qtype": "rearranging formula, factorisation, simplifying and adding algebraic fractions, solving compound inequality",
    "g": "rearrange",
    "src": "0580/42/M/18 Q04",
    "year": 2018,
    "session": "March",
    "tex": "(a) Make $t$ the subject of the formula $s = k - t^2$.\n\\newline\n\n(b) Factorise $x^2 - 25$.\n\\newline\n\n(c) Simplify $\\dfrac{x^2 - 25}{x^2 - 2x - 35}$.\n\\newline\n\n(d) Write as a single fraction in its simplest form.\n\\newline\n\n$\\dfrac{x-8}{x} + \\dfrac{3x}{x+1}$\n\n(e) Find the integer values of $n$ that satisfy the inequality.\n\\newline\n\n$18 - 2n \\leq 6 \\leq 18 - 2n + 12$",
    "parts": [
      {
        "label": "(a)",
        "marks": 2,
        "content": [
          {
            "type": "text",
            "content": "Make $t$ the subject of the formula $s = k - t^2$.\n\\newline\n"
          }
        ],
        "answer": {
          "type": "number",
          "prefix": "$t = $"
        }
      },
      {
        "label": "(b)",
        "marks": 1,
        "content": [
          {
            "type": "text",
            "content": "Factorise $x^2 - 25$.\n\\newline\n"
          }
        ],
        "answer": {
          "type": "number"
        }
      },
      {
        "label": "(c)",
        "marks": 3,
        "content": [
          {
            "type": "text",
            "content": "Simplify $\\dfrac{x^2 - 25}{x^2 - 2x - 35}$.\n\\newline\n"
          }
        ],
        "answer": {
          "type": "number"
        }
      },
      {
        "label": "(d)",
        "marks": 3,
        "content": [
          {
            "type": "text",
            "content": "Write as a single fraction in its simplest form.\n\\newline\n\n$\\dfrac{x-8}{x} + \\dfrac{3x}{x+1}$"
          }
        ],
        "answer": {
          "type": "number"
        }
      },
      {
        "label": "(e)",
        "marks": 3,
        "content": [
          {
            "type": "text",
            "content": "Find the integer values of $n$ that satisfy the inequality.\n\\newline\n\n$18 - 2n \\leq 6 \\leq 18 - 2n + 12$"
          }
        ],
        "answer": {
          "type": "number"
        }
      }
    ],
    "hasFigure": false,
    "cognitive": "analyse",
    "cmd": "simplify",
    "stem": [],
    "_rawBody": "\\begin{parts}\n\\item Make $t$ the subject of the formula $s = k - t^2$.\n\n\\AnswerLine[$t = $][]\n\n\\Marks{2}\n\n\\item Factorise $x^2 - 25$.\n\n\\AnswerLine[][]\n\n\\Marks{1}\n\n\\item Simplify $\\dfrac{x^2 - 25}{x^2 - 2x - 35}$.\n\n\\AnswerLine[][]\n\n\\Marks{3}\n\n\\item Write as a single fraction in its simplest form.\n\n$\\dfrac{x-8}{x} + \\dfrac{3x}{x+1}$\n\n\\AnswerLine[][]\n\n\\Marks{3}\n\n\\item Find the integer values of $n$ that satisfy the inequality.\n\n$18 - 2n \\leq 6 \\leq 18 - 2n + 12$\n\n\\AnswerLine[][]\n\n\\Marks{3}\n\n\\end{parts}",
    "_compactParts": true
  },
  {
    "id": "0580-2018March-Paper42-Q05",
    "paper": "2018March-Paper42",
    "qnum": 5,
    "marks": 11,
    "topics": [
      "Mensuration"
    ],
    "s": "5.4",
    "d": 2,
    "cat": "mensuration",
    "topic": "Volume",
    "qtype": "surface area and volume",
    "g": "mixed",
    "src": "0580/42/M/18 Q05",
    "year": 2018,
    "session": "March",
    "tex": "(a) The diagram shows a solid prism with length 15.2 cm.\n\\newline\nThe cross-section of this prism is a regular hexagon with side 7 cm.\n\\newline\n\n\\begin{InsertScreenShot}\n    [Diagram]\n}\n    }\n\\end{InsertScreenShot}\n\n(i) (b) Calculate the volume of the prism.\n\\newline\n\n(c) Calculate the total surface area of the prism.\n\\newline\n\n(d) Another solid metal prism with volume 500 cm$^3$ is melted and made into 6 identical spheres.\n\\newline\n\nCalculate the radius of each sphere.\n\\newline\n[The volume, $V$, of a sphere with radius $r$ is $V = \\dfrac{4}{3}\\pi r^3$.\n\\newline\n]",
    "parts": [
      {
        "label": "(a)",
        "content": [
          {
            "type": "figure",
            "src": "https://git25math.github.io/25maths-cie0580-figures/2018March/Paper42/Q05/Q05a.png"
          },
          {
            "type": "text",
            "content": "The diagram shows a solid prism with length 15.2 cm.\n\\newline\nThe cross-section of this prism is a regular hexagon with side 7 cm.\n\\newline\n"
          },
          {
            "type": "table",
            "content": "\\begin{InsertScreenShot}\n    \\IfFileExists{\\currfiledir Figures/Q05-HexagonalPrism.png}{\n        \\relincludegraphics{Figures/Q05-HexagonalPrism.png}\n    }{\n        \\fbox{\\parbox{0.4\\textwidth}{\\centering\\vspace{2cm}[Q05-HexagonalPrism.png]\\vspace{2cm}}}\n    }\n\\end{InsertScreenShot}"
          }
        ],
        "subparts": [
          {
            "label": "(i)",
            "marks": 5,
            "content": [
              {
                "type": "text",
                "content": "Calculate the volume of the prism.\n\\newline\n"
              }
            ],
            "answer": {
              "type": "number",
              "suffix": "cm$^3$"
            }
          },
          {
            "label": "(ii)",
            "marks": 3,
            "content": [
              {
                "type": "text",
                "content": "Calculate the total surface area of the prism.\n\\newline\n"
              }
            ],
            "answer": {
              "type": "number",
              "suffix": "cm$^2$"
            }
          }
        ],
        "_subpartCmd": "item"
      },
      {
        "label": "(b)",
        "marks": 3,
        "content": [
          {
            "type": "text",
            "content": "Another solid metal prism with volume 500 cm$^3$ is melted and made into 6 identical spheres.\n\\newline\n\nCalculate the radius of each sphere.\n\\newline\n[The volume, $V$, of a sphere with radius $r$ is $V = \\dfrac{4}{3}\\pi r^3$.\n\\newline\n]"
          }
        ],
        "answer": {
          "type": "number",
          "suffix": "cm"
        }
      }
    ],
    "hasFigure": true,
    "cognitive": "apply",
    "cmd": "calculate",
    "stem": [
      {
        "type": "figure",
        "src": "https://git25math.github.io/25maths-cie0580-figures/2018March/Paper42/Q05/Q05-HexagonalPrism.png"
      }
    ],
    "_rawBody": "\\begin{parts}\n\\item The diagram shows a solid prism with length 15.2 cm.\nThe cross-section of this prism is a regular hexagon with side 7 cm.\n\n\\begin{InsertScreenShot}\n    \\IfFileExists{\\currfiledir Figures/Q05-HexagonalPrism.png}{\n        \\relincludegraphics{Figures/Q05-HexagonalPrism.png}\n    }{\n        \\fbox{\\parbox{0.4\\textwidth}{\\centering\\vspace{2cm}[Q05-HexagonalPrism.png]\\vspace{2cm}}}\n    }\n\\end{InsertScreenShot}\n\n\\begin{subparts}\n\\item Calculate the volume of the prism.\n\n\\AnswerLine[][cm$^3$]\n\n\\Marks{5}\n\n\\item Calculate the total surface area of the prism.\n\n\\AnswerLine[][cm$^2$]\n\n\\Marks{3}\n\n\\end{subparts}\n\n\\item Another solid metal prism with volume 500 cm$^3$ is melted and made into 6 identical spheres.\n\nCalculate the radius of each sphere.\n[The volume, $V$, of a sphere with radius $r$ is $V = \\dfrac{4}{3}\\pi r^3$.]\n\n\\AnswerLine[][cm]\n\n\\Marks{3}\n\n\\end{parts}",
    "_compactParts": true,
    "figureUrls": [
      "https://git25math.github.io/25maths-cie0580-figures/2018March/Paper42/Q05/Q05-HexagonalPrism.png",
      "https://git25math.github.io/25maths-cie0580-figures/2018March/Paper42/Q05/Q05a.png"
    ]
  },
  {
    "id": "0580-2018March-Paper42-Q06",
    "paper": "2018March-Paper42",
    "qnum": 6,
    "marks": 11,
    "topics": [
      "Algebra and graphs"
    ],
    "s": "2.6",
    "d": 2,
    "cat": "algebra",
    "topic": "Inequalities",
    "qtype": "Formulating and graphing linear inequalities",
    "g": "graph",
    "src": "0580/42/M/18 Q06",
    "year": 2018,
    "session": "March",
    "tex": "Klaus buys $x$ silver balloons and $y$ gold balloons for a party.\n\\newline\n\nHe buys\nmore gold balloons than silver balloons\nat least 15 silver balloons\nless than 50 gold balloons\na total of no more than 70 balloons.\n\\newline\n(a) Write down four inequalities, in terms of $x$ and/or $y$, to show this information.\n\\newline\n\n(b) On the grid, show the information from part (a) by drawing four straight lines and shading the\nunwanted regions.\n\\newline\n\n\\begin{InsertScreenShot}\n    [Diagram]\n}\n    }\n\\end{InsertScreenShot}\n\n(c) Silver balloons cost \\$2 and gold balloons cost \\$3.\n\\newline\n\nCalculate the most that Klaus could spend.\n\\newline\n\n\\$",
    "parts": [
      {
        "label": "(a)",
        "marks": 4,
        "content": [
          {
            "type": "text",
            "content": "Write down four inequalities, in terms of $x$ and/or $y$, to show this information.\n\\newline\n"
          }
        ],
        "answer": {
          "type": "multiline",
          "lines": 4,
          "template": "____\\n____\\n____\\n____",
          "lineSep": "blank"
        }
      },
      {
        "label": "(b)",
        "marks": 5,
        "content": [
          {
            "type": "figure",
            "src": "https://git25math.github.io/25maths-cie0580-figures/2018March/Paper42/Q06/Q06b.png"
          },
          {
            "type": "text",
            "content": "On the grid, show the information from part (a) by drawing four straight lines and shading the\nunwanted regions.\n\\newline\n"
          },
          {
            "type": "table",
            "content": "\\begin{InsertScreenShot}\n    \\IfFileExists{\\currfiledir Figures/Q06-InequalityGraph.png}{\n        \\relincludegraphics{Figures/Q06-InequalityGraph.png}\n    }{\n        \\fbox{\\parbox{0.6\\textwidth}{\\centering\\vspace{2cm}[Q06-InequalityGraph.png]\\vspace{2cm}}}\n    }\n\\end{InsertScreenShot}"
          }
        ]
      },
      {
        "label": "(c)",
        "marks": 2,
        "content": [
          {
            "type": "text",
            "content": "Silver balloons cost \\$2 and gold balloons cost \\$3.\n\\newline\n\nCalculate the most that Klaus could spend.\n\\newline\n\n\\$ \\AnswerLine[][]"
          }
        ]
      }
    ],
    "hasFigure": true,
    "cognitive": "apply",
    "cmd": "calculate",
    "stem": [
      {
        "type": "text",
        "content": "Klaus buys $x$ silver balloons and $y$ gold balloons for a party.\n\\newline\n\nHe buys"
      },
      {
        "type": "figure",
        "src": "https://git25math.github.io/25maths-cie0580-figures/2018March/Paper42/Q06/Q06-LargeGraphGrid.png"
      },
      {
        "type": "list",
        "style": "bullet",
        "items": [
          "more gold balloons than silver balloons",
          "at least 15 silver balloons",
          "less than 50 gold balloons",
          "a total of no more than 70 balloons."
        ]
      }
    ],
    "_v4_skip": true,
    "_rawBody": "Klaus buys $x$ silver balloons and $y$ gold balloons for a party.\n\nHe buys\n\\begin{itemize}\n\\item more gold balloons than silver balloons\n\\item at least 15 silver balloons\n\\item less than 50 gold balloons\n\\item a total of no more than 70 balloons.\n\\end{itemize}\n\n\\begin{parts}\n\\item Write down four inequalities, in terms of $x$ and/or $y$, to show this information.\n\n\\AnswerLine[][]\n\n\\AnswerLine[][]\n\n\\AnswerLine[][]\n\n\\AnswerLine[][]\n\n\\Marks{4}\n\n\\item On the grid, show the information from part (a) by drawing four straight lines and shading the\nunwanted regions.\n\n\\begin{InsertScreenShot}\n    \\IfFileExists{\\currfiledir Figures/Q06-InequalityGraph.png}{\n        \\relincludegraphics{Figures/Q06-InequalityGraph.png}\n    }{\n        \\fbox{\\parbox{0.6\\textwidth}{\\centering\\vspace{2cm}[Q06-InequalityGraph.png]\\vspace{2cm}}}\n    }\n\\end{InsertScreenShot}\n\n\\Marks{5}\n\n\\item Silver balloons cost \\$2 and gold balloons cost \\$3.\n\nCalculate the most that Klaus could spend.\n\n\\$ \\AnswerLine[][]\n\n\\Marks{2}\n\n\\end{parts}",
    "_compactParts": true,
    "figureUrls": [
      "https://git25math.github.io/25maths-cie0580-figures/2018March/Paper42/Q06/Q06-LargeGraphGrid.png",
      "https://git25math.github.io/25maths-cie0580-figures/2018March/Paper42/Q06/Q06b.png"
    ]
  },
  {
    "id": "0580-2018March-Paper42-Q07",
    "paper": "2018March-Paper42",
    "qnum": 7,
    "marks": 17,
    "topics": [
      "Probability",
      "Statistics"
    ],
    "s": "8.3",
    "d": 2,
    "cat": "probability",
    "topic": "Tree diagrams",
    "qtype": "combined events",
    "g": "mixed",
    "src": "0580/42/M/18 Q07",
    "year": 2018,
    "session": "March",
    "tex": "The frequency table shows information about the time, $m$ minutes, that each of 160 people spend in a library.\n\\newline\n\n\\begin{tabular}{|l|c|c|c|c|c|c|}\n\\hline\nTime ($m$ minutes) & $0 \\leq m < 10$ & $10 \\leq m < 40$ & $40 \\leq m < 60$ & $60 \\leq m < 90$ & $90 \\leq m < 100$ & $100 \\leq m < 120$ \\\\\n\\hline\nFrequency & 3 & 39 & 43 & 55 & 11 & 9 \\\\\n\\hline\n\\end{tabular}\n\n(a) Find the probability that one of these people, chosen at random, spends more than 100 minutes in\nthe library.\n\\newline\n\n(b) Calculate an estimate of the mean time spent in the library.\n\\newline\n\n minutes\n\n(c) Complete the cumulative frequency table below.\n\\newline\n\n\\begin{tabular}{|l|c|c|c|c|c|c|}\n\\hline\nTime ($m$ minutes) & $m < 10$ & $m < 40$ & $m < 60$ & $m < 90$ & $m < 100$ & $m < 120$ \\\\\n\\hline\nCumulative frequency & 3 & 42 & & & & \\\\\n\\hline\n\\end{tabular}\n\n(d) On the grid opposite, draw the cumulative frequency diagram.\n\\newline\n\n\\begin{InsertScreenShot}\n    [Diagram]\n}\n    }\n\\end{InsertScreenShot}\n\n(e) Use your cumulative frequency diagram to find\n\n(i) (f) the median,\n\n minutes\n\n(g) the interquartile range,\n\n minutes\n\n(h) the 90th percentile,\n\n minutes\n\n(i) the number of people who spend more than 30 minutes in the library.\n\\newline\n",
    "parts": [
      {
        "label": "(a)",
        "marks": 1,
        "content": [
          {
            "type": "text",
            "content": "Find the probability that one of these people, chosen at random, spends more than 100 minutes in\nthe library.\n\\newline\n"
          }
        ],
        "answer": {
          "type": "number"
        }
      },
      {
        "label": "(b)",
        "marks": 4,
        "content": [
          {
            "type": "figure",
            "src": "https://git25math.github.io/25maths-cie0580-figures/2018March/Paper42/Q07/Q07b.png"
          },
          {
            "type": "text",
            "content": "Calculate an estimate of the mean time spent in the library.\n\\newline\n"
          }
        ],
        "answer": {
          "type": "number"
        }
      },
      {
        "label": "(c)",
        "marks": 2,
        "content": [
          {
            "type": "figure",
            "src": "https://git25math.github.io/25maths-cie0580-figures/2018March/Paper42/Q07/Q07c.png"
          },
          {
            "type": "text",
            "content": "Complete the cumulative frequency table below.\n\\newline\n"
          },
          {
            "type": "table",
            "content": "\\begin{tabular}{|l|c|c|c|c|c|c|}\n\\hline\nTime ($m$ minutes) & $m < 10$ & $m < 40$ & $m < 60$ & $m < 90$ & $m < 100$ & $m < 120$ \\\\\n\\hline\nCumulative frequency & 3 & 42 & & & & \\\\\n\\hline\n\\end{tabular}"
          }
        ]
      },
      {
        "label": "(d)",
        "marks": 3,
        "content": [
          {
            "type": "text",
            "content": "On the grid opposite, draw the cumulative frequency diagram.\n\\newline\n"
          },
          {
            "type": "table",
            "content": "\\begin{InsertScreenShot}\n    \\IfFileExists{\\currfiledir Figures/Q07-CumulativeFrequency.png}{\n        \\relincludegraphics{Figures/Q07-CumulativeFrequency.png}\n    }{\n        \\fbox{\\parbox{0.7\\textwidth}{\\centering\\vspace{2cm}[Q07-CumulativeFrequency.png]\\vspace{2cm}}}\n    }\n\\end{InsertScreenShot}"
          }
        ]
      },
      {
        "label": "(e)",
        "content": [
          {
            "type": "text",
            "content": "Use your cumulative frequency diagram to find"
          }
        ],
        "subparts": [
          {
            "label": "(i)",
            "marks": 1,
            "content": [
              {
                "type": "text",
                "content": "the median,"
              }
            ],
            "answer": {
              "type": "number"
            }
          },
          {
            "label": "(ii)",
            "marks": 2,
            "content": [
              {
                "type": "text",
                "content": "the interquartile range,"
              }
            ],
            "answer": {
              "type": "number"
            }
          },
          {
            "label": "(iii)",
            "marks": 2,
            "content": [
              {
                "type": "text",
                "content": "the 90th percentile,"
              }
            ],
            "answer": {
              "type": "number"
            }
          },
          {
            "label": "(iv)",
            "marks": 2,
            "content": [
              {
                "type": "text",
                "content": "the number of people who spend more than 30 minutes in the library.\n\\newline\n"
              }
            ],
            "answer": {
              "type": "number"
            }
          }
        ],
        "_subpartCmd": "item"
      }
    ],
    "hasFigure": true,
    "cognitive": "apply",
    "cmd": "draw",
    "stem": [
      {
        "type": "text",
        "content": "The frequency table shows information about the time, $m$ minutes, that each of 160 people spend in a library.\n\\newline\n"
      },
      {
        "type": "figure",
        "src": "https://git25math.github.io/25maths-cie0580-figures/2018March/Paper42/Q07/Q07.png"
      },
      {
        "type": "figure",
        "src": "https://git25math.github.io/25maths-cie0580-figures/2018March/Paper42/Q07/Q07-CumulativeFreqGrid.png"
      },
      {
        "type": "table",
        "content": "\\begin{tabular}{|l|c|c|c|c|c|c|}\n\\hline\nTime ($m$ minutes) & $0 \\leq m < 10$ & $10 \\leq m < 40$ & $40 \\leq m < 60$ & $60 \\leq m < 90$ & $90 \\leq m < 100$ & $100 \\leq m < 120$ \\\\\n\\hline\nFrequency & 3 & 39 & 43 & 55 & 11 & 9 \\\\\n\\hline\n\\end{tabular}"
      }
    ],
    "_rawBody": "The frequency table shows information about the time, $m$ minutes, that each of 160 people spend in a library.\n\n\\begin{tabular}{|l|c|c|c|c|c|c|}\n\\hline\nTime ($m$ minutes) & $0 \\leq m < 10$ & $10 \\leq m < 40$ & $40 \\leq m < 60$ & $60 \\leq m < 90$ & $90 \\leq m < 100$ & $100 \\leq m < 120$ \\\\\n\\hline\nFrequency & 3 & 39 & 43 & 55 & 11 & 9 \\\\\n\\hline\n\\end{tabular}\n\n\\begin{parts}\n\\item Find the probability that one of these people, chosen at random, spends more than 100 minutes in\nthe library.\n\n\\AnswerLine[][]\n\n\\Marks{1}\n\n\\item Calculate an estimate of the mean time spent in the library.\n\n\\AnswerLine[][] minutes\n\n\\Marks{4}\n\n\\item Complete the cumulative frequency table below.\n\n\\begin{tabular}{|l|c|c|c|c|c|c|}\n\\hline\nTime ($m$ minutes) & $m < 10$ & $m < 40$ & $m < 60$ & $m < 90$ & $m < 100$ & $m < 120$ \\\\\n\\hline\nCumulative frequency & 3 & 42 & & & & \\\\\n\\hline\n\\end{tabular}\n\n\\Marks{2}\n\n\\item On the grid opposite, draw the cumulative frequency diagram.\n\n\\begin{InsertScreenShot}\n    \\IfFileExists{\\currfiledir Figures/Q07-CumulativeFrequency.png}{\n        \\relincludegraphics{Figures/Q07-CumulativeFrequency.png}\n    }{\n        \\fbox{\\parbox{0.7\\textwidth}{\\centering\\vspace{2cm}[Q07-CumulativeFrequency.png]\\vspace{2cm}}}\n    }\n\\end{InsertScreenShot}\n\n\\Marks{3}\n\n\\item Use your cumulative frequency diagram to find\n\n\\begin{subparts}\n\\item the median,\n\n\\AnswerLine[][] minutes\n\n\\Marks{1}\n\n\\item the interquartile range,\n\n\\AnswerLine[][] minutes\n\n\\Marks{2}\n\n\\item the 90th percentile,\n\n\\AnswerLine[][] minutes\n\n\\Marks{2}\n\n\\item the number of people who spend more than 30 minutes in the library.\n\n\\AnswerLine[][]\n\n\\Marks{2}\n\n\\end{subparts}\n\n\\end{parts}",
    "_compactParts": true,
    "figureUrls": [
      "https://git25math.github.io/25maths-cie0580-figures/2018March/Paper42/Q07/Q07-CumulativeFreqGrid.png",
      "https://git25math.github.io/25maths-cie0580-figures/2018March/Paper42/Q07/Q07-CumulativeFreqTable.png",
      "https://git25math.github.io/25maths-cie0580-figures/2018March/Paper42/Q07/Q07-FrequencyTable.png",
      "https://git25math.github.io/25maths-cie0580-figures/2018March/Paper42/Q07/Q07.png",
      "https://git25math.github.io/25maths-cie0580-figures/2018March/Paper42/Q07/Q07b.png",
      "https://git25math.github.io/25maths-cie0580-figures/2018March/Paper42/Q07/Q07c.png"
    ]
  },
  {
    "id": "0580-2018March-Paper42-Q08",
    "paper": "2018March-Paper42",
    "qnum": 8,
    "marks": 10,
    "topics": [
      "Geometry",
      "Trigonometry"
    ],
    "s": "4.3",
    "d": 2,
    "cat": "geometry",
    "topic": "Symmetry",
    "qtype": "scale drawings and bearings",
    "g": "mixed",
    "src": "0580/42/M/18 Q08",
    "year": 2018,
    "session": "March",
    "tex": "The diagram shows two ports, L and P, and a buoy, M.\n\\newline\nThe bearing of L from P is 201$^\\circ$ and LP = 248 km.\n\\newline\nThe bearing of M from P is 127$^\\circ$.\n\\newline\nAngle PML = 42$^\\circ$.\n\\newline\n\n\\begin{InsertScreenShot}\n    [Diagram]\n}\n    }\n\\end{InsertScreenShot}\n\n(a) Use the sine rule to calculate LM.\n\\newline\n\nLM =  km\n\n(b) A ship sails directly from L to P.\n\\newline\n\n(i) (c) Calculate the shortest distance from M to LP.\n\\newline\n\n km\n\n(d) The ship leaves L at 20 45 and travels at a speed of 40 km/h.\n\\newline\n\nCalculate the time the next day that the ship arrives at P.\n\\newline\n",
    "parts": [
      {
        "label": "(a)",
        "marks": 4,
        "content": [
          {
            "type": "text",
            "content": "Use the sine rule to calculate LM.\n\\newline\n\nLM = \\AnswerLine[][] km"
          }
        ]
      },
      {
        "label": "(b)",
        "content": [
          {
            "type": "text",
            "content": "A ship sails directly from L to P.\n\\newline\n"
          }
        ],
        "subparts": [
          {
            "label": "(i)",
            "marks": 3,
            "content": [
              {
                "type": "text",
                "content": "Calculate the shortest distance from M to LP.\n\\newline\n"
              }
            ],
            "answer": {
              "type": "number"
            }
          },
          {
            "label": "(ii)",
            "marks": 3,
            "content": [
              {
                "type": "text",
                "content": "The ship leaves L at 20 45 and travels at a speed of 40 km/h.\n\\newline\n\nCalculate the time the next day that the ship arrives at P.\n\\newline\n"
              }
            ],
            "answer": {
              "type": "number"
            }
          }
        ],
        "_subpartCmd": "item"
      }
    ],
    "hasFigure": true,
    "cognitive": "apply",
    "cmd": "calculate",
    "stem": [
      {
        "type": "text",
        "content": "The diagram shows two ports, L and P, and a buoy, M.\n\\newline\nThe bearing of L from P is 201$^\\circ$ and LP = 248 km.\n\\newline\nThe bearing of M from P is 127$^\\circ$.\n\\newline\nAngle PML = 42$^\\circ$.\n\\newline\n"
      },
      {
        "type": "figure",
        "src": "https://git25math.github.io/25maths-cie0580-figures/2018March/Paper42/Q08/Q08.png"
      },
      {
        "type": "figure",
        "src": "https://git25math.github.io/25maths-cie0580-figures/2018March/Paper42/Q08/Q08-BearingTriangle.png"
      },
      {
        "type": "table",
        "content": "\\begin{InsertScreenShot}\n    \\IfFileExists{\\currfiledir Figures/Q08-Bearings.png}{\n        \\relincludegraphics{Figures/Q08-Bearings.png}\n    }{\n        \\fbox{\\parbox{0.5\\textwidth}{\\centering\\vspace{2cm}[Q08-Bearings.png]\\vspace{2cm}}}\n    }\n\\end{InsertScreenShot}"
      }
    ],
    "_rawBody": "The diagram shows two ports, L and P, and a buoy, M.\nThe bearing of L from P is 201$^\\circ$ and LP = 248 km.\nThe bearing of M from P is 127$^\\circ$.\nAngle PML = 42$^\\circ$.\n\n\\begin{InsertScreenShot}\n    \\IfFileExists{\\currfiledir Figures/Q08-Bearings.png}{\n        \\relincludegraphics{Figures/Q08-Bearings.png}\n    }{\n        \\fbox{\\parbox{0.5\\textwidth}{\\centering\\vspace{2cm}[Q08-Bearings.png]\\vspace{2cm}}}\n    }\n\\end{InsertScreenShot}\n\n\\begin{parts}\n\\item Use the sine rule to calculate LM.\n\nLM = \\AnswerLine[][] km\n\n\\Marks{4}\n\n\\item A ship sails directly from L to P.\n\n\\begin{subparts}\n\\item Calculate the shortest distance from M to LP.\n\n\\AnswerLine[][] km\n\n\\Marks{3}\n\n\\item The ship leaves L at 20 45 and travels at a speed of 40 km/h.\n\nCalculate the time the next day that the ship arrives at P.\n\n\\AnswerLine[][]\n\n\\Marks{3}\n\n\\end{subparts}\n\n\\end{parts}",
    "_compactParts": true,
    "figureUrls": [
      "https://git25math.github.io/25maths-cie0580-figures/2018March/Paper42/Q08/Q08-BearingTriangle.png",
      "https://git25math.github.io/25maths-cie0580-figures/2018March/Paper42/Q08/Q08.png"
    ]
  },
  {
    "id": "0580-2018March-Paper42-Q09",
    "paper": "2018March-Paper42",
    "qnum": 9,
    "marks": 12,
    "topics": [
      "Algebra and graphs",
      "Transformations and vectors"
    ],
    "s": null,
    "d": 2,
    "cat": "algebra",
    "topic": null,
    "qtype": "Vectors and Matrices (Not an algebra subtopic)",
    "g": "mixed",
    "src": "0580/42/M/18 Q09",
    "year": 2018,
    "session": "March",
    "tex": "(a) Find the magnitude of the vector $\\begin{pmatrix} -1 \\\\ 7 \\end{pmatrix}$.\n\\newline\n\n(b) The determinant of the matrix $\\begin{pmatrix} 6 & 2m \\\\ 5 & m \\end{pmatrix}$ is 24.\n\\newline\n\nFind the value of $m$.\n\\newline\n\n(c) $L = \\begin{pmatrix} 2 & 5 \\end{pmatrix}$, $M = \\begin{pmatrix} -4 \\\\ 2 \\end{pmatrix}$, $N = \\begin{pmatrix} 3 & 9 \\end{pmatrix}$.\n\\newline\n\nWork out the following.\n\\newline\n\n(i) (d) $NM$\n\n(e) $LM$\n\n(f) $L^2$\n\n(g) $L^{-1}$",
    "parts": [
      {
        "label": "(a)",
        "marks": 2,
        "content": [
          {
            "type": "text",
            "content": "Find the magnitude of the vector $\\begin{pmatrix} -1 \\\\ 7 \\end{pmatrix}$.\n\\newline\n"
          }
        ],
        "answer": {
          "type": "number"
        }
      },
      {
        "label": "(b)",
        "marks": 2,
        "content": [
          {
            "type": "text",
            "content": "The determinant of the matrix $\\begin{pmatrix} 6 & 2m \\\\ 5 & m \\end{pmatrix}$ is 24.\n\\newline\n\nFind the value of $m$.\n\\newline\n"
          }
        ],
        "answer": {
          "type": "number",
          "prefix": "$m = $"
        }
      },
      {
        "label": "(c)",
        "content": [
          {
            "type": "text",
            "content": "$L = \\begin{pmatrix} 2 & 5 \\end{pmatrix}$, $M = \\begin{pmatrix} -4 \\\\ 2 \\end{pmatrix}$, $N = \\begin{pmatrix} 3 & 9 \\end{pmatrix}$.\n\\newline\n\nWork out the following.\n\\newline\n"
          }
        ],
        "subparts": [
          {
            "label": "(i)",
            "marks": 2,
            "content": [
              {
                "type": "text",
                "content": "$NM$"
              }
            ],
            "answer": {
              "type": "number"
            }
          },
          {
            "label": "(ii)",
            "marks": 2,
            "content": [
              {
                "type": "text",
                "content": "$LM$"
              }
            ],
            "answer": {
              "type": "number"
            }
          },
          {
            "label": "(iii)",
            "marks": 2,
            "content": [
              {
                "type": "text",
                "content": "$L^2$"
              }
            ],
            "answer": {
              "type": "number"
            }
          },
          {
            "label": "(iv)",
            "marks": 2,
            "content": [
              {
                "type": "text",
                "content": "$L^{-1}$"
              }
            ],
            "answer": {
              "type": "number"
            }
          }
        ],
        "_subpartCmd": "item"
      }
    ],
    "hasFigure": false,
    "cognitive": "apply",
    "cmd": "calculate",
    "stem": [],
    "_rawBody": "\\begin{parts}\n\\item Find the magnitude of the vector $\\begin{pmatrix} -1 \\\\ 7 \\end{pmatrix}$.\n\n\\AnswerLine[][]\n\n\\Marks{2}\n\n\\item The determinant of the matrix $\\begin{pmatrix} 6 & 2m \\\\ 5 & m \\end{pmatrix}$ is 24.\n\nFind the value of $m$.\n\n\\AnswerLine[$m = $][]\n\n\\Marks{2}\n\n\\item $L = \\begin{pmatrix} 2 & 5 \\end{pmatrix}$, $M = \\begin{pmatrix} -4 \\\\ 2 \\end{pmatrix}$, $N = \\begin{pmatrix} 3 & 9 \\end{pmatrix}$.\n\nWork out the following.\n\n\\begin{subparts}\n\\item $NM$\n\n\\AnswerLine[][]\n\n\\Marks{2}\n\n\\item $LM$\n\n\\AnswerLine[][]\n\n\\Marks{2}\n\n\\item $L^2$\n\n\\AnswerLine[][]\n\n\\Marks{2}\n\n\\item $L^{-1}$\n\n\\AnswerLine[][]\n\n\\Marks{2}\n\n\\end{subparts}\n\n\\end{parts}",
    "_compactParts": true
  },
  {
    "id": "0580-2018March-Paper42-Q10",
    "paper": "2018March-Paper42",
    "qnum": 10,
    "marks": 10,
    "topics": [
      "Coordinate geometry"
    ],
    "s": "3.7",
    "d": 2,
    "cat": "coord",
    "topic": "Coordinate geometry extended",
    "qtype": "perpendicular lines",
    "g": "mixed",
    "src": "0580/42/M/18 Q10",
    "year": 2018,
    "session": "March",
    "tex": "(a) Calculate the length of AB.\n\\newline\n\n\\begin{InsertScreenShot}\n    [Diagram]\n}\n    }\n\\end{InsertScreenShot}\n\n(b) The point P has co-ordinates $(10, 12)$ and the point Q has co-ordinates $(2, -4)$.\n\\newline\n\n(i) (c) Find the co-ordinates of the mid-point of the line PQ.\n\\newline\n\n(d) Find the gradient of the line PQ.\n\\newline\n\n(e) Find the equation of a line perpendicular to PQ that passes through the point $(2, 3)$.\n\\newline\n",
    "parts": [
      {
        "label": "(a)",
        "marks": 3,
        "content": [
          {
            "type": "figure",
            "src": "https://git25math.github.io/25maths-cie0580-figures/2018March/Paper42/Q10/Q10a.png"
          },
          {
            "type": "text",
            "content": "Calculate the length of AB.\n\\newline\n"
          },
          {
            "type": "table",
            "content": "\\begin{InsertScreenShot}\n    \\IfFileExists{\\currfiledir Figures/Q10-CoordinateGrid.png}{\n        \\relincludegraphics{Figures/Q10-CoordinateGrid.png}\n    }{\n        \\fbox{\\parbox{0.4\\textwidth}{\\centering\\vspace{2cm}[Q10-CoordinateGrid.png]\\vspace{2cm}}}\n    }\n\\end{InsertScreenShot}"
          }
        ],
        "answer": {
          "type": "number"
        }
      },
      {
        "label": "(b)",
        "content": [
          {
            "type": "text",
            "content": "The point P has co-ordinates $(10, 12)$ and the point Q has co-ordinates $(2, -4)$.\n\\newline\n"
          }
        ],
        "subparts": [
          {
            "label": "(i)",
            "marks": 2,
            "content": [
              {
                "type": "text",
                "content": "Find the co-ordinates of the mid-point of the line PQ.\n\\newline\n"
              }
            ],
            "answer": {
              "type": "number",
              "suffix": "(....., .....)"
            }
          },
          {
            "label": "(ii)",
            "marks": 2,
            "content": [
              {
                "type": "text",
                "content": "Find the gradient of the line PQ.\n\\newline\n"
              }
            ],
            "answer": {
              "type": "number"
            }
          },
          {
            "label": "(iii)",
            "marks": 3,
            "content": [
              {
                "type": "text",
                "content": "Find the equation of a line perpendicular to PQ that passes through the point $(2, 3)$.\n\\newline\n"
              }
            ],
            "answer": {
              "type": "number"
            }
          }
        ],
        "_subpartCmd": "item"
      }
    ],
    "hasFigure": true,
    "cognitive": "apply",
    "cmd": "calculate",
    "stem": [
      {
        "type": "figure",
        "src": "https://git25math.github.io/25maths-cie0580-figures/2018March/Paper42/Q10/Q10-LineAB.png"
      }
    ],
    "_rawBody": "\\begin{parts}\n\\item Calculate the length of AB.\n\n\\begin{InsertScreenShot}\n    \\IfFileExists{\\currfiledir Figures/Q10-CoordinateGrid.png}{\n        \\relincludegraphics{Figures/Q10-CoordinateGrid.png}\n    }{\n        \\fbox{\\parbox{0.4\\textwidth}{\\centering\\vspace{2cm}[Q10-CoordinateGrid.png]\\vspace{2cm}}}\n    }\n\\end{InsertScreenShot}\n\n\\AnswerLine[][]\n\n\\Marks{3}\n\n\\item The point P has co-ordinates $(10, 12)$ and the point Q has co-ordinates $(2, -4)$.\n\n\\begin{subparts}\n\\item Find the co-ordinates of the mid-point of the line PQ.\n\n\\AnswerLine[][(....., .....)]\n\n\\Marks{2}\n\n\\item Find the gradient of the line PQ.\n\n\\AnswerLine[][]\n\n\\Marks{2}\n\n\\item Find the equation of a line perpendicular to PQ that passes through the point $(2, 3)$.\n\n\\AnswerLine[][]\n\n\\Marks{3}\n\n\\end{subparts}\n\n\\end{parts}",
    "_compactParts": true,
    "figureUrls": [
      "https://git25math.github.io/25maths-cie0580-figures/2018March/Paper42/Q10/Q10-LineAB.png",
      "https://git25math.github.io/25maths-cie0580-figures/2018March/Paper42/Q10/Q10a.png"
    ]
  },
  {
    "id": "0580-2018March-Paper42-Q11",
    "paper": "2018March-Paper42",
    "qnum": 11,
    "marks": 13,
    "topics": [
      "Algebra and graphs"
    ],
    "s": "2.7",
    "d": 2,
    "cat": "algebra",
    "topic": "Sequences",
    "qtype": "Finding nth term of sequences, solving for n",
    "g": "sequence",
    "src": "0580/42/M/18 Q11",
    "year": 2018,
    "session": "March",
    "tex": "The table shows the first five terms of sequences A, B and C.\n\\newline\n\n\\begin{tabular}{|l|c|c|c|c|c|c|}\n\\hline\nSequence & 1st term & 2nd term & 3rd term & 4th term & 5th term & 6th term \\\\\n\\hline\nA & 0 & 1 & 4 & 9 & 16 & \\\\\n\\hline\nB & 4 & 5 & 6 & 7 & 8 & \\\\\n\\hline\nC & -4 & -4 & -2 & 2 & 8 & \\\\\n\\hline\n\\end{tabular}\n\n(a) Complete the table.\n\\newline\n\n(b) Find an expression for the nth term of\n\n(i) (c) sequence A,\n\n(d) sequence B.\n\\newline\n\n(e) Find the value of $n$ when the nth term of sequence A is 576.\n\\newline\n\n(f) Find an expression for the nth term of sequence C.\n\\newline\nGive your answer in its simplest form.\n\\newline\n\n(i) (g) Expression:\n\n(h) Find the value of the 30th term of sequence C.\n\\newline\n",
    "parts": [
      {
        "label": "(a)",
        "marks": 3,
        "content": [
          {
            "type": "text",
            "content": "Complete the table.\n\\newline\n"
          }
        ]
      },
      {
        "label": "(b)",
        "content": [
          {
            "type": "text",
            "content": "Find an expression for the nth term of"
          }
        ],
        "subparts": [
          {
            "label": "(i)",
            "marks": 2,
            "content": [
              {
                "type": "text",
                "content": "sequence A,"
              }
            ],
            "answer": {
              "type": "number"
            }
          },
          {
            "label": "(ii)",
            "marks": 1,
            "content": [
              {
                "type": "text",
                "content": "sequence B.\n\\newline\n"
              }
            ],
            "answer": {
              "type": "number"
            }
          }
        ],
        "_subpartCmd": "item"
      },
      {
        "label": "(c)",
        "marks": 2,
        "content": [
          {
            "type": "text",
            "content": "Find the value of $n$ when the nth term of sequence A is 576.\n\\newline\n"
          }
        ],
        "answer": {
          "type": "number",
          "prefix": "$n = $"
        }
      },
      {
        "label": "(d)",
        "content": [
          {
            "type": "text",
            "content": "Find an expression for the nth term of sequence C.\n\\newline\nGive your answer in its simplest form.\n\\newline\n"
          }
        ],
        "subparts": [
          {
            "label": "(i)",
            "marks": 3,
            "content": [
              {
                "type": "text",
                "content": "Expression:"
              }
            ],
            "answer": {
              "type": "number"
            }
          },
          {
            "label": "(ii)",
            "marks": 2,
            "content": [
              {
                "type": "text",
                "content": "Find the value of the 30th term of sequence C.\n\\newline\n"
              }
            ],
            "answer": {
              "type": "number"
            }
          }
        ],
        "_subpartCmd": "item"
      }
    ],
    "hasFigure": true,
    "cognitive": "apply",
    "cmd": "complete",
    "stem": [
      {
        "type": "text",
        "content": "The table shows the first five terms of sequences A, B and C.\n\\newline\n"
      },
      {
        "type": "figure",
        "src": "https://git25math.github.io/25maths-cie0580-figures/2018March/Paper42/Q11/Q11.png"
      },
      {
        "type": "table",
        "content": "\\begin{tabular}{|l|c|c|c|c|c|c|}\n\\hline\nSequence & 1st term & 2nd term & 3rd term & 4th term & 5th term & 6th term \\\\\n\\hline\nA & 0 & 1 & 4 & 9 & 16 & \\\\\n\\hline\nB & 4 & 5 & 6 & 7 & 8 & \\\\\n\\hline\nC & -4 & -4 & -2 & 2 & 8 & \\\\\n\\hline\n\\end{tabular}"
      }
    ],
    "_rawBody": "The table shows the first five terms of sequences A, B and C.\n\n\\begin{tabular}{|l|c|c|c|c|c|c|}\n\\hline\nSequence & 1st term & 2nd term & 3rd term & 4th term & 5th term & 6th term \\\\\n\\hline\nA & 0 & 1 & 4 & 9 & 16 & \\\\\n\\hline\nB & 4 & 5 & 6 & 7 & 8 & \\\\\n\\hline\nC & -4 & -4 & -2 & 2 & 8 & \\\\\n\\hline\n\\end{tabular}\n\n\\begin{parts}\n\\item Complete the table.\n\n\\Marks{3}\n\n\\item Find an expression for the nth term of\n\n\\begin{subparts}\n\\item sequence A,\n\n\\AnswerLine[][]\n\n\\Marks{2}\n\n\\item sequence B.\n\n\\AnswerLine[][]\n\n\\Marks{1}\n\n\\end{subparts}\n\n\\item Find the value of $n$ when the nth term of sequence A is 576.\n\n\\AnswerLine[$n = $][]\n\n\\Marks{2}\n\n\\item Find an expression for the nth term of sequence C.\nGive your answer in its simplest form.\n\n\\begin{subparts}\n\\item Expression:\n\n\\AnswerLine[][]\n\n\\Marks{3}\n\n\\item Find the value of the 30th term of sequence C.\n\n\\AnswerLine[][]\n\n\\Marks{2}\n\n\\end{subparts}\n\n\\end{parts}",
    "_compactParts": true,
    "figureUrls": [
      "https://git25math.github.io/25maths-cie0580-figures/2018March/Paper42/Q11/Q11-SequenceTable.png",
      "https://git25math.github.io/25maths-cie0580-figures/2018March/Paper42/Q11/Q11.png"
    ]
  }
]