[
  {
    "id": "0580-2023OctNov-Paper11-Q01",
    "paper": "2023OctNov-Paper11",
    "qnum": 1,
    "marks": 1,
    "topics": [
      "Geometry",
      "Statistics"
    ],
    "s": "4.6",
    "d": 1,
    "cat": "geometry",
    "topic": "Constructions",
    "qtype": "angle calculations",
    "g": "mixed",
    "src": "0580/11/O/N/23 Q01",
    "year": 2023,
    "session": "OctNov",
    "tex": "\\begin{InsertScreenShot}\n\n\\end{InsertScreenShot}\n\nWrite down the mathematical name for this type of angle.\n\\newline\n",
    "parts": [],
    "hasFigure": true,
    "cognitive": "recall",
    "cmd": "write",
    "stem": [
      {
        "type": "table",
        "content": "\\begin{InsertScreenShot}\n    \\relincludegraphics{Figures/Q01-Angle.png}\n\\end{InsertScreenShot}"
      },
      {
        "type": "text",
        "content": "\\StemText{\nWrite down the mathematical name for this type of angle.\n\\newline\n}"
      },
      {
        "type": "figure",
        "src": "https://git25math.github.io/25maths-cie0580-figures/2023OctNov/Paper11/Q01/Q01.png"
      },
      {
        "type": "figure",
        "src": "https://git25math.github.io/25maths-cie0580-figures/2023OctNov/Paper11/Q01/Q01-Angle.png"
      }
    ],
    "answer": {
      "type": "number"
    },
    "_rawBody": "\\begin{InsertScreenShot}\n    \\relincludegraphics{Figures/Q01-Angle.png}\n\\end{InsertScreenShot}\n\n\\StemText{\nWrite down the mathematical name for this type of angle.\n}\n\n\\AnswerLine[][]\n\\Marks{1}",
    "_compactMarks": true,
    "figureUrls": [
      "https://git25math.github.io/25maths-cie0580-figures/2023OctNov/Paper11/Q01/Q01-Angle.png",
      "https://git25math.github.io/25maths-cie0580-figures/2023OctNov/Paper11/Q01/Q01.png"
    ]
  },
  {
    "id": "0580-2023OctNov-Paper11-Q02",
    "paper": "2023OctNov-Paper11",
    "qnum": 2,
    "marks": 1,
    "topics": [
      "Statistics"
    ],
    "s": "9.3",
    "d": 1,
    "cat": "statistics",
    "topic": "Frequency tables",
    "qtype": "averages and spread",
    "g": "mixed",
    "src": "0580/11/O/N/23 Q02",
    "year": 2023,
    "session": "OctNov",
    "tex": "Write down the value of the 8 in the number $58\\,317$.\n\\newline\n",
    "parts": [],
    "hasFigure": false,
    "cognitive": "recall",
    "cmd": "write",
    "stem": [
      {
        "type": "text",
        "content": "\\StemText{\nWrite down the value of the 8 in the number $58\\,317$.\n\\newline\n}"
      }
    ],
    "answer": {
      "type": "number"
    },
    "_rawBody": "\\StemText{\nWrite down the value of the 8 in the number 58\\,317.\n}\n\n\\AnswerLine[][]\n\\Marks{1}",
    "_compactMarks": true
  },
  {
    "id": "0580-2023OctNov-Paper11-Q03",
    "paper": "2023OctNov-Paper11",
    "qnum": 3,
    "marks": 3,
    "topics": [
      "Statistics"
    ],
    "s": "9.3",
    "d": 1,
    "cat": "statistics",
    "topic": "Frequency tables",
    "qtype": "averages and spread",
    "g": "mixed",
    "src": "0580/11/O/N/23 Q03",
    "year": 2023,
    "session": "OctNov",
    "tex": "Complete these statements.\n\\newline\n}\n\n(a) When $x = \\dots\\dots\\dots\\dots\\dots$, $x + 3 = 8$.\n\\newline\n\n(b) When $7y = 63$, $10y = \\dots\\dots\\dots\\dots\\dots$",
    "parts": [
      {
        "label": "(a)",
        "marks": 1,
        "content": [
          {
            "type": "text",
            "content": "When $x = \\dots\\dots\\dots\\dots\\dots$, $x + 3 = 8$.\n\\newline\n"
          }
        ],
        "answer": {
          "type": "number"
        },
        "_compactMarks": true
      },
      {
        "label": "(b)",
        "marks": 1,
        "content": [
          {
            "type": "text",
            "content": "When $7y = 63$, $10y = \\dots\\dots\\dots\\dots\\dots$"
          }
        ],
        "answer": {
          "type": "number"
        },
        "_compactMarks": true
      }
    ],
    "hasFigure": false,
    "cognitive": "recall",
    "cmd": "complete",
    "stem": [
      {
        "type": "text",
        "content": "\\StemText{\nComplete these statements.\n\\newline\n}"
      }
    ],
    "_rawBody": "\\StemText{\nComplete these statements.\n}\n\n\\begin{parts}\n\\item When $x = \\dots\\dots\\dots\\dots\\dots$, $x + 3 = 8$.\n\n\\AnswerLine[][]\n\\Marks{1}\n\n\\item When $7y = 63$, $10y = \\dots\\dots\\dots\\dots\\dots$\n\n\\AnswerLine[][]\n\\Marks{1}\n\\end{parts}",
    "_compactParts": true,
    "_compactEndParts": true
  },
  {
    "id": "0580-2023OctNov-Paper11-Q04",
    "paper": "2023OctNov-Paper11",
    "qnum": 4,
    "marks": 1,
    "topics": [
      "Statistics"
    ],
    "s": "9.3",
    "d": 1,
    "cat": "statistics",
    "topic": "Frequency tables",
    "qtype": "averages and spread",
    "g": "mixed",
    "src": "0580/11/O/N/23 Q04",
    "year": 2023,
    "session": "OctNov",
    "tex": "Find the value of $\\sqrt[3]{5832}$.\n\\newline\n",
    "parts": [],
    "hasFigure": false,
    "cognitive": "apply",
    "cmd": "find",
    "stem": [
      {
        "type": "text",
        "content": "\\StemText{\nFind the value of $\\sqrt[3]{5832}$.\n\\newline\n}"
      }
    ],
    "answer": {
      "type": "number"
    },
    "_rawBody": "\\StemText{\nFind the value of $\\sqrt[3]{5832}$.\n}\n\n\\AnswerLine[][]\n\\Marks{1}",
    "_compactMarks": true
  },
  {
    "id": "0580-2023OctNov-Paper11-Q05",
    "paper": "2023OctNov-Paper11",
    "qnum": 5,
    "marks": 1,
    "topics": [
      "Statistics"
    ],
    "s": "9.3",
    "d": 1,
    "cat": "statistics",
    "topic": "Frequency tables",
    "qtype": "averages and spread",
    "g": "mixed",
    "src": "0580/11/O/N/23 Q05",
    "year": 2023,
    "session": "OctNov",
    "tex": "A watch costs \\$$12\\,400$.\n\\newline\n\\\\\nIn a sale there is a discount of 16\\%.\n\\newline\n}\n\nCalculate the amount of the discount.\n\\newline\n",
    "parts": [],
    "hasFigure": false,
    "cognitive": "apply",
    "cmd": "calculate",
    "stem": [
      {
        "type": "text",
        "content": "\\StemText{\nA watch costs \\$$12\\,400$.\n\\newline\n\\\\\nIn a sale there is a discount of 16\\%.\n\\newline\n}\n\n\\StemText{\nCalculate the amount of the discount.\n\\newline\n}"
      }
    ],
    "answer": {
      "type": "number",
      "prefix": "\\$"
    },
    "_rawBody": "\\StemText{\nA watch costs \\$12\\,400.\\\\\nIn a sale there is a discount of 16\\%.\n}\n\n\\StemText{\nCalculate the amount of the discount.\n}\n\n\\AnswerLine[\\$][]\n\\Marks{1}",
    "_compactMarks": true
  },
  {
    "id": "0580-2023OctNov-Paper11-Q06",
    "paper": "2023OctNov-Paper11",
    "qnum": 6,
    "marks": 6,
    "topics": [
      "Number",
      "Statistics"
    ],
    "s": "1.1",
    "d": 1,
    "cat": "number",
    "topic": "Types of number",
    "qtype": "Properties of integers (range, median, mode), mean calculation",
    "g": "mixed",
    "src": "0580/11/O/N/23 Q06",
    "year": 2023,
    "session": "OctNov",
    "tex": "(a) Mei writes down five integers.\n\\newline\n\n(b) The lowest integer is 8.\n\\newline\n\n(c) The range is 9.\n\\newline\n\n(d) The median is 15.\n\\newline\n\n(e) The total of the five integers is 66.\n\\newline\n\n(f) There is no mode.\n\\newline\n\nWrite down the five integers.\n\\newline\n}\n\nHuan writes down four numbers.\n\\newline\n\\\\\nThe mean of these four numbers is 17.\n\\newline\n\nHe writes down a fifth number.\n\\newline\n\\\\\nThe mean of these five numbers is 20.\n\\newline\n}\n\nFind the fifth number.\n\\newline\n}",
    "parts": [
      {
        "label": "(a)",
        "marks": 0,
        "content": [
          {
            "type": "text",
            "content": "Mei writes down five integers.\n\\newline\n\n\\begin{parts}"
          }
        ]
      },
      {
        "label": "(b)",
        "marks": 0,
        "content": [
          {
            "type": "text",
            "content": "The lowest integer is 8.\n\\newline\n"
          }
        ]
      },
      {
        "label": "(c)",
        "marks": 0,
        "content": [
          {
            "type": "text",
            "content": "The range is 9.\n\\newline\n"
          }
        ]
      },
      {
        "label": "(d)",
        "marks": 0,
        "content": [
          {
            "type": "text",
            "content": "The median is 15.\n\\newline\n"
          }
        ]
      },
      {
        "label": "(e)",
        "marks": 0,
        "content": [
          {
            "type": "text",
            "content": "The total of the five integers is 66.\n\\newline\n"
          }
        ]
      },
      {
        "label": "(f)",
        "marks": 0,
        "content": [
          {
            "type": "text",
            "content": "There is no mode.\n\\newline\n"
          }
        ]
      }
    ],
    "hasFigure": false,
    "cognitive": "apply",
    "cmd": "find",
    "stem": [],
    "_v4_skip": true,
    "_rawBody": "\\begin{parts}\n\\item Mei writes down five integers.\n\n\\begin{parts}\n    \\item The lowest integer is 8.\n    \\item The range is 9.\n    \\item The median is 15.\n    \\item The total of the five integers is 66.\n    \\item There is no mode.\n\\end{parts}\n\n\\StemText{\nWrite down the five integers.\n}\n\n\\AnswerLine[~~~~~~~~][, , , , ]\n\\Marks{3}\n\n\\item Huan writes down four numbers.\\\\\nThe mean of these four numbers is 17.\n\n\\StemText{\nHe writes down a fifth number.\\\\\nThe mean of these five numbers is 20.\n}\n\n\\StemText{\nFind the fifth number.\n}\n\n\\AnswerLine[][]\n\\Marks{3}\n\\end{parts}",
    "_compactParts": true,
    "_compactEndParts": true,
    "_postParts": [
      {
        "type": "text",
        "content": "\\StemText{\nWrite down the five integers.\n}\n\n\\AnswerLine[~~~~~~~~][, , , , ]\n\\Marks{3}\n\n\\item Huan writes down four numbers.\\\\\nThe mean of these four numbers is 17.\n\n\\StemText{\nHe writes down a fifth number.\\\\\nThe mean of these five numbers is 20.\n}\n\n\\StemText{\nFind the fifth number.\n}\n\n\\AnswerLine[][]\n\\Marks{3}\n\\end{parts}"
      }
    ],
    "_compactBegin": true,
    "_compactItems": true
  },
  {
    "id": "0580-2023OctNov-Paper11-Q07",
    "paper": "2023OctNov-Paper11",
    "qnum": 7,
    "marks": 2,
    "topics": [
      "Statistics"
    ],
    "s": "9.3",
    "d": 1,
    "cat": "statistics",
    "topic": "Frequency tables",
    "qtype": "averages and spread",
    "g": "mixed",
    "src": "0580/11/O/N/23 Q07",
    "year": 2023,
    "session": "OctNov",
    "tex": "Arjun lives in Delhi and Haru lives in Tokyo.\n\\newline\n\\\\\nThey play a computer game online at the same time.\n\\newline\n}\n\nThey start at 14$\\,$45 Tokyo local time.\n\\newline\n\\\\\nThe game lasts 3 hours 50 minutes.\n\\newline\n\\\\\nThe local time in Delhi is 3 hours 30 minutes behind the local time in Tokyo.\n\\newline\n}\n\nFind the local time in Delhi when the game finishes.\n\\newline\n",
    "parts": [],
    "hasFigure": false,
    "cognitive": "apply",
    "cmd": "find",
    "stem": [
      {
        "type": "text",
        "content": "\\StemText{\nArjun lives in Delhi and Haru lives in Tokyo.\n\\newline\n\\\\\nThey play a computer game online at the same time.\n\\newline\n}\n\n\\StemText{\nThey start at 14$\\,$45 Tokyo local time.\n\\newline\n\\\\\nThe game lasts 3 hours 50 minutes.\n\\newline\n\\\\\nThe local time in Delhi is 3 hours 30 minutes behind the local time in Tokyo.\n\\newline\n}\n\n\\StemText{\nFind the local time in Delhi when the game finishes.\n\\newline\n}"
      }
    ],
    "answer": {
      "type": "number"
    },
    "_rawBody": "\\StemText{\nArjun lives in Delhi and Haru lives in Tokyo.\\\\\nThey play a computer game online at the same time.\n}\n\n\\StemText{\nThey start at 14\\,45 Tokyo local time.\\\\\nThe game lasts 3 hours 50 minutes.\\\\\nThe local time in Delhi is 3 hours 30 minutes behind the local time in Tokyo.\n}\n\n\\StemText{\nFind the local time in Delhi when the game finishes.\n}\n\n\\AnswerLine[][]\n\\Marks{2}",
    "_compactMarks": true
  },
  {
    "id": "0580-2023OctNov-Paper11-Q08",
    "paper": "2023OctNov-Paper11",
    "qnum": 8,
    "marks": 2,
    "topics": [
      "Geometry",
      "Statistics"
    ],
    "s": "4.6",
    "d": 1,
    "cat": "geometry",
    "topic": "Constructions",
    "qtype": "angle calculations",
    "g": "mixed",
    "src": "0580/11/O/N/23 Q08",
    "year": 2023,
    "session": "OctNov",
    "tex": "The diagram shows an isosceles triangle.\n\\newline\n}\n\n\\begin{InsertScreenShot}\n\n\\end{InsertScreenShot}\n\nFind the value of $x$.\n\\newline\n",
    "parts": [],
    "hasFigure": true,
    "cognitive": "apply",
    "cmd": "find",
    "stem": [
      {
        "type": "text",
        "content": "\\StemText{\nThe diagram shows an isosceles triangle.\n\\newline\n}"
      },
      {
        "type": "table",
        "content": "\\begin{InsertScreenShot}\n    \\relincludegraphics{Figures/Q08-Triangle.png}\n\\end{InsertScreenShot}"
      },
      {
        "type": "text",
        "content": "\\StemText{\nFind the value of $x$.\n\\newline\n}"
      },
      {
        "type": "figure",
        "src": "https://git25math.github.io/25maths-cie0580-figures/2023OctNov/Paper11/Q08/Q08.png"
      },
      {
        "type": "figure",
        "src": "https://git25math.github.io/25maths-cie0580-figures/2023OctNov/Paper11/Q08/Q08-Triangle.png"
      }
    ],
    "answer": {
      "type": "number",
      "prefix": "$x = $"
    },
    "_rawBody": "\\StemText{\nThe diagram shows an isosceles triangle.\n}\n\n\\begin{InsertScreenShot}\n    \\relincludegraphics{Figures/Q08-Triangle.png}\n\\end{InsertScreenShot}\n\n\\StemText{\nFind the value of $x$.\n}\n\n\\AnswerLine[$x = $][]\n\\Marks{2}",
    "_compactMarks": true,
    "figureUrls": [
      "https://git25math.github.io/25maths-cie0580-figures/2023OctNov/Paper11/Q08/Q08-Triangle.png",
      "https://git25math.github.io/25maths-cie0580-figures/2023OctNov/Paper11/Q08/Q08.png"
    ]
  },
  {
    "id": "0580-2023OctNov-Paper11-Q09",
    "paper": "2023OctNov-Paper11",
    "qnum": 9,
    "marks": 9,
    "topics": [
      "Statistics"
    ],
    "s": "9.4",
    "d": 1,
    "cat": "statistics",
    "topic": "Charts and graphs",
    "qtype": "statistical charts",
    "g": "mixed",
    "src": "0580/11/O/N/23 Q09",
    "year": 2023,
    "session": "OctNov",
    "tex": "The stem-and-leaf diagram shows the time, in minutes, it takes each of 15 people to complete a race.\n\\newline\n}\n\n\\begin{tabular}{r|llllllllll}\n1 & 6 & 6 & 7 & & & & & & & \\\\\n2 & 1 & 3 & 3 & 4 & 5 & 6 & 7 & 7 & 7 \\\\\n3 & 0 & 1 & 1 & & & & & & & \\\\\n\\end{tabular}\n Key: $1 \\mid 6$ represents 16 minutes\n\nFind\n}\n\n(a) the mode,\n\n(b) the range,\n\n(c) the median.\n\\newline\n",
    "parts": [
      {
        "label": "(a)",
        "marks": 1,
        "content": [
          {
            "type": "text",
            "content": "the mode,"
          }
        ],
        "answer": {
          "type": "number",
          "suffix": "min"
        },
        "_compactMarks": true
      },
      {
        "label": "(b)",
        "marks": 1,
        "content": [
          {
            "type": "text",
            "content": "the range,"
          }
        ],
        "answer": {
          "type": "number",
          "suffix": "min"
        },
        "_compactMarks": true
      },
      {
        "label": "(c)",
        "marks": 1,
        "content": [
          {
            "type": "text",
            "content": "the median.\n\\newline\n"
          }
        ],
        "answer": {
          "type": "number",
          "suffix": "min"
        },
        "_compactMarks": true
      }
    ],
    "hasFigure": true,
    "cognitive": "apply",
    "cmd": "complete",
    "stem": [
      {
        "type": "text",
        "content": "\\StemText{\nThe stem-and-leaf diagram shows the time, in minutes, it takes each of 15 people to complete a race.\n\\newline\n}"
      },
      {
        "type": "table",
        "content": "\\begin{center}\n\\begin{tabular}{r|llllllllll}\n1 & 6 & 6 & 7 & & & & & & & \\\\\n2 & 1 & 3 & 3 & 4 & 5 & 6 & 7 & 7 & 7 \\\\\n3 & 0 & 1 & 1 & & & & & & & \\\\\n\\end{tabular}\n\\end{center}"
      },
      {
        "type": "text",
        "content": "\\hfill Key: $1 \\mid 6$ represents 16 minutes\n\n\\StemText{\nFind\n}"
      },
      {
        "type": "figure",
        "src": "https://git25math.github.io/25maths-cie0580-figures/2023OctNov/Paper11/Q09/Q09.png"
      }
    ],
    "_rawBody": "\\StemText{\nThe stem-and-leaf diagram shows the time, in minutes, it takes each of 15 people to complete a race.\n}\n\n\\begin{center}\n\\begin{tabular}{r|llllllllll}\n1 & 6 & 6 & 7 & & & & & & & \\\\\n2 & 1 & 3 & 3 & 4 & 5 & 6 & 7 & 7 & 7 \\\\\n3 & 0 & 1 & 1 & & & & & & & \\\\\n\\end{tabular}\n\\end{center}\n\\hfill Key: $1 \\mid 6$ represents 16 minutes\n\n\\StemText{\nFind\n}\n\n\\begin{parts}\n\\item the mode,\n\n\\AnswerLine[][min]\n\\Marks{1}\n\n\\item the range,\n\n\\AnswerLine[][min]\n\\Marks{1}\n\n\\item the median.\n\n\\AnswerLine[][min]\n\\Marks{1}\n\\end{parts}",
    "_compactParts": true,
    "_compactEndParts": true,
    "figureUrls": [
      "https://git25math.github.io/25maths-cie0580-figures/2023OctNov/Paper11/Q09/Q09.png"
    ]
  },
  {
    "id": "0580-2023OctNov-Paper11-Q10",
    "paper": "2023OctNov-Paper11",
    "qnum": 10,
    "marks": 2,
    "topics": [
      "Geometry",
      "Statistics"
    ],
    "s": "4.6",
    "d": 1,
    "cat": "geometry",
    "topic": "Constructions",
    "qtype": "angle calculations",
    "g": "mixed",
    "src": "0580/11/O/N/23 Q10",
    "year": 2023,
    "session": "OctNov",
    "tex": "\\begin{InsertScreenShot}\n\n\\end{InsertScreenShot}\n\n$AB$ and $CD$ are parallel lines.\n\\newline\n}\n\nFind the value of $x$.\n\\newline\n",
    "parts": [],
    "hasFigure": true,
    "cognitive": "apply",
    "cmd": "find",
    "stem": [
      {
        "type": "table",
        "content": "\\begin{InsertScreenShot}\n    \\relincludegraphics{Figures/Q10-ParallelLines.png}\n\\end{InsertScreenShot}"
      },
      {
        "type": "text",
        "content": "\\StemText{\n$AB$ and $CD$ are parallel lines.\n\\newline\n}\n\n\\StemText{\nFind the value of $x$.\n\\newline\n}"
      },
      {
        "type": "figure",
        "src": "https://git25math.github.io/25maths-cie0580-figures/2023OctNov/Paper11/Q10/Q10.png"
      },
      {
        "type": "figure",
        "src": "https://git25math.github.io/25maths-cie0580-figures/2023OctNov/Paper11/Q10/Q10-ParallelLines.png"
      }
    ],
    "answer": {
      "type": "number",
      "prefix": "$x = $"
    },
    "_rawBody": "\\begin{InsertScreenShot}\n    \\relincludegraphics{Figures/Q10-ParallelLines.png}\n\\end{InsertScreenShot}\n\\StemText{\n$AB$ and $CD$ are parallel lines.\n}\n\n\\StemText{\nFind the value of $x$.\n}\n\n\\AnswerLine[$x = $][]\n\\Marks{2}",
    "_compactMarks": true,
    "figureUrls": [
      "https://git25math.github.io/25maths-cie0580-figures/2023OctNov/Paper11/Q10/Q10-ParallelLines.png",
      "https://git25math.github.io/25maths-cie0580-figures/2023OctNov/Paper11/Q10/Q10.png"
    ]
  },
  {
    "id": "0580-2023OctNov-Paper11-Q11",
    "paper": "2023OctNov-Paper11",
    "qnum": 11,
    "marks": 1,
    "topics": [
      "Number",
      "Statistics"
    ],
    "s": "1.9",
    "d": 1,
    "cat": "number",
    "topic": "Percentages",
    "qtype": "rounding to significant figures",
    "g": "mixed",
    "src": "0580/11/O/N/23 Q11",
    "year": 2023,
    "session": "OctNov",
    "tex": "Write 0.03682 correct to 2 significant figures.\n\\newline\n",
    "parts": [],
    "hasFigure": false,
    "cognitive": "apply",
    "cmd": "write",
    "stem": [
      {
        "type": "text",
        "content": "\\StemText{\nWrite 0.03682 correct to 2 significant figures.\n\\newline\n}"
      }
    ],
    "answer": {
      "type": "number"
    },
    "_rawBody": "\\StemText{\nWrite 0.03682 correct to 2 significant figures.\n}\n\n\\AnswerLine[][]\n\\Marks{1}",
    "_compactMarks": true
  },
  {
    "id": "0580-2023OctNov-Paper11-Q12",
    "paper": "2023OctNov-Paper11",
    "qnum": 12,
    "marks": 3,
    "topics": [
      "Statistics"
    ],
    "s": "9.3",
    "d": 1,
    "cat": "statistics",
    "topic": "Frequency tables",
    "qtype": "averages and spread",
    "g": "mixed",
    "src": "0580/11/O/N/23 Q12",
    "year": 2023,
    "session": "OctNov",
    "tex": "The table shows some information about Amir's shopping.\n\\newline\n}\n\n\\begin{tabular}{|l|c|c|c|}\n\\hline\n**Fruit** & **Cost per kilogram** & **Number of kilograms Amir buys** & **Cost** \\\\\n\\hline\nOranges & \\$2.35 & 3.2 & \\$\\dots\\dots\\dots\\dots\\dots \\\\\n\\hline\nBananas & \\$\\dots\\dots\\dots\\dots\\dots & 2.8 & \\$\\dots\\dots\\dots\\dots\\dots \\\\\n\\hline\n\\multicolumn{3}{|r|}{**Total**} & \\$13.54 \\\\\n\\hline\n\\end{tabular}\n\nComplete the table.\n\\newline\n",
    "parts": [],
    "hasFigure": true,
    "cognitive": "recall",
    "cmd": "complete",
    "stem": [
      {
        "type": "text",
        "content": "\\StemText{\nThe table shows some information about Amir's shopping.\n\\newline\n}"
      },
      {
        "type": "table",
        "content": "\\begin{center}\n\\begin{tabular}{|l|c|c|c|}\n\\hline\n\\textbf{Fruit} & \\textbf{Cost per kilogram} & \\textbf{Number of kilograms Amir buys} & \\textbf{Cost} \\\\\n\\hline\nOranges & \\$2.35 & 3.2 & \\$\\dots\\dots\\dots\\dots\\dots \\\\\n\\hline\nBananas & \\$\\dots\\dots\\dots\\dots\\dots & 2.8 & \\$\\dots\\dots\\dots\\dots\\dots \\\\\n\\hline\n\\multicolumn{3}{|r|}{\\textbf{Total}} & \\$13.54 \\\\\n\\hline\n\\end{tabular}\n\\end{center}"
      },
      {
        "type": "text",
        "content": "\\StemText{\nComplete the table.\n\\newline\n}"
      },
      {
        "type": "figure",
        "src": "https://git25math.github.io/25maths-cie0580-figures/2023OctNov/Paper11/Q12/Q12.png"
      }
    ],
    "_rawBody": "\\StemText{\nThe table shows some information about Amir's shopping.\n}\n\n\\begin{center}\n\\begin{tabular}{|l|c|c|c|}\n\\hline\n\\textbf{Fruit} & \\textbf{Cost per kilogram} & \\textbf{Number of kilograms Amir buys} & \\textbf{Cost} \\\\\n\\hline\nOranges & \\$2.35 & 3.2 & \\$\\dots\\dots\\dots\\dots\\dots \\\\\n\\hline\nBananas & \\$\\dots\\dots\\dots\\dots\\dots & 2.8 & \\$\\dots\\dots\\dots\\dots\\dots \\\\\n\\hline\n\\multicolumn{3}{|r|}{\\textbf{Total}} & \\$13.54 \\\\\n\\hline\n\\end{tabular}\n\\end{center}\n\n\\StemText{\nComplete the table.\n}\n\n\\Marks{3}",
    "figureUrls": [
      "https://git25math.github.io/25maths-cie0580-figures/2023OctNov/Paper11/Q12/Q12.png"
    ]
  },
  {
    "id": "0580-2023OctNov-Paper11-Q13",
    "paper": "2023OctNov-Paper11",
    "qnum": 13,
    "marks": 13,
    "topics": [
      "Statistics"
    ],
    "s": "9.5",
    "d": 1,
    "cat": "statistics",
    "topic": "Scatter diagrams",
    "qtype": "scatter diagrams",
    "g": "mixed",
    "src": "0580/11/O/N/23 Q13",
    "year": 2023,
    "session": "OctNov",
    "tex": "For each of 10 people working in an office, the scatter diagram shows their salary and the value of their car.\n\\newline\n}\n\n\\begin{InsertScreenShot}\n\n\\end{InsertScreenShot}\n\n(a) One of these people has a salary of \\$$28\\,000$.\n\\newline\n\nFind the value of their car.\n\\newline\n}\n\n(b) Another person starts to work in the office.\n\\newline\n\\\\\nTheir salary is \\$$54\\,000$ and the value of their car is \\$6100.\n\\newline\n\nPlot this information on the scatter diagram.\n\\newline\n}\n\n(c) What type of correlation is shown in the scatter diagram?",
    "parts": [
      {
        "label": "(a)",
        "marks": 1,
        "content": [
          {
            "type": "text",
            "content": "One of these people has a salary of \\$$28\\,000$.\n\\newline\n\n\\StemText{\nFind the value of their car.\n\\newline\n}"
          }
        ],
        "answer": {
          "type": "number",
          "prefix": "\\$"
        },
        "_compactMarks": true
      },
      {
        "label": "(b)",
        "marks": 1,
        "content": [
          {
            "type": "text",
            "content": "Another person starts to work in the office.\n\\newline\n\\\\\nTheir salary is \\$$54\\,000$ and the value of their car is \\$6100.\n\\newline\n\n\\StemText{\nPlot this information on the scatter diagram.\n\\newline\n}"
          }
        ]
      },
      {
        "label": "(c)",
        "marks": 1,
        "content": [
          {
            "type": "text",
            "content": "What type of correlation is shown in the scatter diagram?"
          }
        ],
        "answer": {
          "type": "number"
        },
        "_compactMarks": true
      }
    ],
    "hasFigure": true,
    "cognitive": "apply",
    "cmd": "draw",
    "stem": [
      {
        "type": "text",
        "content": "\\StemText{\nFor each of 10 people working in an office, the scatter diagram shows their salary and the value of their car.\n\\newline\n}"
      },
      {
        "type": "figure",
        "src": "https://git25math.github.io/25maths-cie0580-figures/2023OctNov/Paper11/Q13/Q13.png"
      },
      {
        "type": "figure",
        "src": "https://git25math.github.io/25maths-cie0580-figures/2023OctNov/Paper11/Q13/Q13-ScatterDiagram.png"
      },
      {
        "type": "table",
        "content": "\\begin{InsertScreenShot}\n    \\relincludegraphics{Figures/Q13-ScatterDiagram.png}\n\\end{InsertScreenShot}"
      }
    ],
    "_rawBody": "\\StemText{\nFor each of 10 people working in an office, the scatter diagram shows their salary and the value of their car.\n}\n\n\\begin{InsertScreenShot}\n    \\relincludegraphics{Figures/Q13-ScatterDiagram.png}\n\\end{InsertScreenShot}\n\n\\begin{parts}\n\\item One of these people has a salary of \\$28\\,000.\n\n\\StemText{\nFind the value of their car.\n}\n\n\\AnswerLine[\\$][]\n\\Marks{1}\n\n\\item Another person starts to work in the office.\\\\\nTheir salary is \\$54\\,000 and the value of their car is \\$6100.\n\n\\StemText{\nPlot this information on the scatter diagram.\n}\n\n\\Marks{1}\n\n\\item What type of correlation is shown in the scatter diagram?\n\n\\AnswerLine[][]\n\\Marks{1}\n\\end{parts}",
    "_compactParts": true,
    "_compactEndParts": true,
    "figureUrls": [
      "https://git25math.github.io/25maths-cie0580-figures/2023OctNov/Paper11/Q13/Q13-ScatterDiagram.png",
      "https://git25math.github.io/25maths-cie0580-figures/2023OctNov/Paper11/Q13/Q13.png"
    ]
  },
  {
    "id": "0580-2023OctNov-Paper11-Q14",
    "paper": "2023OctNov-Paper11",
    "qnum": 14,
    "marks": 2,
    "topics": [
      "Number",
      "Algebra and graphs",
      "Statistics"
    ],
    "s": "2.2",
    "d": 1,
    "cat": "algebra",
    "topic": "Rearranging formulae",
    "qtype": "algebraic factorisation",
    "g": "simplify",
    "src": "0580/11/O/N/23 Q14",
    "year": 2023,
    "session": "OctNov",
    "tex": "Factorise completely.\n\\newline\n}\n$$ 42mk - 35m $$",
    "parts": [],
    "hasFigure": false,
    "cognitive": "apply",
    "cmd": "simplify",
    "stem": [
      {
        "type": "text",
        "content": "\\StemText{\nFactorise completely.\n\\newline\n}\n$$ 42mk - 35m $$"
      }
    ],
    "answer": {
      "type": "number"
    },
    "_rawBody": "\\StemText{\nFactorise completely.\n}\n$$ 42mk - 35m $$\n\n\\AnswerLine[][]\n\\Marks{2}",
    "_compactMarks": true
  },
  {
    "id": "0580-2023OctNov-Paper11-Q15",
    "paper": "2023OctNov-Paper11",
    "qnum": 15,
    "marks": 2,
    "topics": [
      "Number",
      "Statistics"
    ],
    "s": "1.1",
    "d": 1,
    "cat": "number",
    "topic": "Types of number",
    "qtype": "HCF calculation",
    "g": "mixed",
    "src": "0580/11/O/N/23 Q15",
    "year": 2023,
    "session": "OctNov",
    "tex": "Find the highest common factor (HCF) of 140 and 126.\n\\newline\n",
    "parts": [],
    "hasFigure": false,
    "cognitive": "apply",
    "cmd": "find",
    "stem": [
      {
        "type": "text",
        "content": "\\StemText{\nFind the highest common factor (HCF) of 140 and 126.\n\\newline\n}"
      }
    ],
    "answer": {
      "type": "number"
    },
    "_rawBody": "\\StemText{\nFind the highest common factor (HCF) of 140 and 126.\n}\n\n\\AnswerLine[][]\n\\Marks{2}",
    "_compactMarks": true
  },
  {
    "id": "0580-2023OctNov-Paper11-Q16",
    "paper": "2023OctNov-Paper11",
    "qnum": 16,
    "marks": 16,
    "topics": [
      "Algebra and graphs",
      "Statistics"
    ],
    "s": "2.4",
    "d": 1,
    "cat": "algebra",
    "topic": "Algebraic fractions",
    "qtype": "simplifying expressions with indices",
    "g": "simplify",
    "src": "0580/11/O/N/23 Q16",
    "year": 2023,
    "session": "OctNov",
    "tex": "Simplify.\n\\newline\n}\n\n(a) $n^5 \\times n$\n\n(b) $8x^6 \\div 2x^2$",
    "parts": [
      {
        "label": "(a)",
        "marks": 1,
        "content": [
          {
            "type": "text",
            "content": "$n^5 \\times n$"
          }
        ],
        "answer": {
          "type": "number"
        },
        "_compactMarks": true
      },
      {
        "label": "(b)",
        "marks": 2,
        "content": [
          {
            "type": "text",
            "content": "$8x^6 \\div 2x^2$"
          }
        ],
        "answer": {
          "type": "number"
        },
        "_compactMarks": true
      }
    ],
    "hasFigure": false,
    "cognitive": "apply",
    "cmd": "simplify",
    "stem": [
      {
        "type": "text",
        "content": "\\StemText{\nSimplify.\n\\newline\n}"
      }
    ],
    "_rawBody": "\\StemText{\nSimplify.\n}\n\n\\begin{parts}\n\\item $n^5 \\times n$\n\n\\AnswerLine[][]\n\\Marks{1}\n\n\\item $8x^6 \\div 2x^2$\n\n\\AnswerLine[][]\n\\Marks{2}\n\n\\end{parts}",
    "_compactParts": true
  },
  {
    "id": "0580-2023OctNov-Paper11-Q17",
    "paper": "2023OctNov-Paper11",
    "qnum": 17,
    "marks": 2,
    "topics": [
      "Geometry",
      "Mensuration",
      "Statistics"
    ],
    "s": "4.6",
    "d": 1,
    "cat": "geometry",
    "topic": "Constructions",
    "qtype": "angle calculations",
    "g": "mixed",
    "src": "0580/11/O/N/23 Q17",
    "year": 2023,
    "session": "OctNov",
    "tex": "The circumference of a circle is 59 cm.\n\\newline\n}\n\nCalculate the radius of the circle.\n\\newline\n",
    "parts": [],
    "hasFigure": false,
    "cognitive": "apply",
    "cmd": "calculate",
    "stem": [
      {
        "type": "text",
        "content": "\\StemText{\nThe circumference of a circle is 59 cm.\n\\newline\n}\n\n\\StemText{\nCalculate the radius of the circle.\n\\newline\n}"
      }
    ],
    "answer": {
      "type": "number",
      "suffix": "cm"
    },
    "_rawBody": "\\StemText{\nThe circumference of a circle is 59 cm.\n}\n\n\\StemText{\nCalculate the radius of the circle.\n}\n\n\\AnswerLine[][cm]\n\\Marks{2}",
    "_compactMarks": true
  },
  {
    "id": "0580-2023OctNov-Paper11-Q18",
    "paper": "2023OctNov-Paper11",
    "qnum": 18,
    "marks": 2,
    "topics": [
      "Number",
      "Statistics"
    ],
    "s": "1.9",
    "d": 1,
    "cat": "number",
    "topic": "Percentages",
    "qtype": "estimation by rounding to significant figures",
    "g": "mixed",
    "src": "0580/11/O/N/23 Q18",
    "year": 2023,
    "session": "OctNov",
    "tex": "By writing each number in the calculation correct to 1 significant figure, find an estimate for the value of \n$$ \\frac{36.9 + 24.2}{3.8 - 1.2}.\n\\newline\n $$\nYou must show all your working.\n\\newline\n",
    "parts": [],
    "hasFigure": false,
    "cognitive": "apply",
    "cmd": "calculate",
    "stem": [
      {
        "type": "text",
        "content": "\\StemText{\nBy writing each number in the calculation correct to 1 significant figure, find an estimate for the value of \n$$ \\frac{36.9 + 24.2}{3.8 - 1.2}.\n\\newline\n $$\nYou must show all your working.\n\\newline\n}"
      }
    ],
    "answer": {
      "type": "number"
    },
    "_rawBody": "\\StemText{\nBy writing each number in the calculation correct to 1 significant figure, find an estimate for the value of \n$$ \\frac{36.9 + 24.2}{3.8 - 1.2}. $$\nYou must show all your working.\n}\n\n\\AnswerLine[][]\n\\Marks{2}",
    "_compactMarks": true
  },
  {
    "id": "0580-2023OctNov-Paper11-Q19",
    "paper": "2023OctNov-Paper11",
    "qnum": 19,
    "marks": 3,
    "topics": [
      "Number",
      "Statistics"
    ],
    "s": "1.13",
    "d": 1,
    "cat": "number",
    "topic": "Electronic calculators",
    "qtype": "simple interest calculation",
    "g": "mixed",
    "src": "0580/11/O/N/23 Q19",
    "year": 2023,
    "session": "OctNov",
    "tex": "Indira invests \\$6000 at a rate of $r$\\% per year simple interest.\n\\newline\n\\\\\nAt the end of 4 years the value of her investment is \\$6840.\n\\newline\n}\n\nFind the value of $r$.\n\\newline\n",
    "parts": [],
    "hasFigure": false,
    "cognitive": "apply",
    "cmd": "find",
    "stem": [
      {
        "type": "text",
        "content": "\\StemText{\nIndira invests \\$6000 at a rate of $r$\\% per year simple interest.\n\\newline\n\\\\\nAt the end of 4 years the value of her investment is \\$6840.\n\\newline\n}\n\n\\StemText{\nFind the value of $r$.\n\\newline\n}"
      }
    ],
    "answer": {
      "type": "number",
      "prefix": "$r = $"
    },
    "_rawBody": "\\StemText{\nIndira invests \\$6000 at a rate of $r$\\% per year simple interest.\\\\\nAt the end of 4 years the value of her investment is \\$6840.\n}\n\n\\StemText{\nFind the value of $r$.\n}\n\n\\AnswerLine[$r = $][]\n\\Marks{3}",
    "_compactMarks": true
  },
  {
    "id": "0580-2023OctNov-Paper11-Q20",
    "paper": "2023OctNov-Paper11",
    "qnum": 20,
    "marks": 2,
    "topics": [
      "Geometry",
      "Mensuration",
      "Statistics"
    ],
    "s": "4.6",
    "d": 1,
    "cat": "geometry",
    "topic": "Constructions",
    "qtype": "angle calculations",
    "g": "mixed",
    "src": "0580/11/O/N/23 Q20",
    "year": 2023,
    "session": "OctNov",
    "tex": "\\begin{InsertScreenShot}\n\n\\end{InsertScreenShot}\n\nFind the area of this trapezium.\n\\newline\n",
    "parts": [],
    "hasFigure": true,
    "cognitive": "apply",
    "cmd": "find",
    "stem": [
      {
        "type": "table",
        "content": "\\begin{InsertScreenShot}\n    \\relincludegraphics{Figures/Q20-Trapezium.png}\n\\end{InsertScreenShot}"
      },
      {
        "type": "text",
        "content": "\\StemText{\nFind the area of this trapezium.\n\\newline\n}"
      },
      {
        "type": "figure",
        "src": "https://git25math.github.io/25maths-cie0580-figures/2023OctNov/Paper11/Q20/Q20.png"
      },
      {
        "type": "figure",
        "src": "https://git25math.github.io/25maths-cie0580-figures/2023OctNov/Paper11/Q20/Q20-Trapezium.png"
      }
    ],
    "answer": {
      "type": "number",
      "suffix": "cm$^2$"
    },
    "_rawBody": "\\begin{InsertScreenShot}\n    \\relincludegraphics{Figures/Q20-Trapezium.png}\n\\end{InsertScreenShot}\n\n\\StemText{\nFind the area of this trapezium.\n}\n\n\\AnswerLine[][cm$^2$]\n\\Marks{2}",
    "_compactMarks": true,
    "figureUrls": [
      "https://git25math.github.io/25maths-cie0580-figures/2023OctNov/Paper11/Q20/Q20-Trapezium.png",
      "https://git25math.github.io/25maths-cie0580-figures/2023OctNov/Paper11/Q20/Q20.png"
    ]
  },
  {
    "id": "0580-2023OctNov-Paper11-Q21",
    "paper": "2023OctNov-Paper11",
    "qnum": 21,
    "marks": 21,
    "topics": [
      "Number"
    ],
    "s": "1.8",
    "d": 1,
    "cat": "number",
    "topic": "Ratio, rate and proportion",
    "qtype": "standard form conversion and calculation",
    "g": "mixed",
    "src": "0580/11/O/N/23 Q21",
    "year": 2023,
    "session": "OctNov",
    "tex": "(a) Write these numbers in standard form.\n\\newline\n\n(i) (b) $45\\,000$\n\n(c) 0.0063\n\n(d) Calculate $8.2 \\times 10^{-1} \\times 150\\,000$.\n\\newline\nGive your answer in standard form.\n\\newline\n",
    "parts": [
      {
        "label": "(a)",
        "content": [
          {
            "type": "text",
            "content": "Write these numbers in standard form.\n\\newline\n"
          }
        ],
        "subparts": [
          {
            "label": "(i)",
            "marks": 1,
            "content": [
              {
                "type": "text",
                "content": "$45\\,000$"
              }
            ],
            "answer": {
              "type": "number"
            },
            "_compactMarks": true
          },
          {
            "label": "(ii)",
            "marks": 1,
            "content": [
              {
                "type": "text",
                "content": "0.0063"
              }
            ],
            "answer": {
              "type": "number"
            },
            "_compactMarks": true
          }
        ],
        "_subpartCmd": "item",
        "_compactEndSubparts": true
      },
      {
        "label": "(b)",
        "marks": 2,
        "content": [
          {
            "type": "text",
            "content": "Calculate $8.2 \\times 10^{-1} \\times 150\\,000$.\n\\newline\nGive your answer in standard form.\n\\newline\n"
          }
        ],
        "answer": {
          "type": "number"
        },
        "_compactMarks": true
      }
    ],
    "hasFigure": false,
    "cognitive": "apply",
    "cmd": "calculate",
    "stem": [],
    "_rawBody": "\\begin{parts}\n\\item Write these numbers in standard form.\n\n\\begin{subparts}\n\\item 45\\,000\n\n\\AnswerLine[][]\n\\Marks{1}\n\n\\item 0.0063\n\n\\AnswerLine[][]\n\\Marks{1}\n\\end{subparts}\n\n\\item Calculate $8.2 \\times 10^{-1} \\times 150\\,000$.\nGive your answer in standard form.\n\n\\AnswerLine[][]\n\\Marks{2}\n\n\\end{parts}",
    "_compactParts": true,
    "_compactBegin": true
  },
  {
    "id": "0580-2023OctNov-Paper11-Q22",
    "paper": "2023OctNov-Paper11",
    "qnum": 22,
    "marks": 2,
    "topics": [
      "Statistics"
    ],
    "s": "9.3",
    "d": 1,
    "cat": "statistics",
    "topic": "Frequency tables",
    "qtype": "averages and spread",
    "g": "mixed",
    "src": "0580/11/O/N/23 Q22",
    "year": 2023,
    "session": "OctNov",
    "tex": "The length, $s$ metres, of a ship is 287 m, correct to the nearest metre.\n\\newline\n}\n\nComplete this statement about the value of $s$.\n\\newline\n",
    "parts": [],
    "hasFigure": false,
    "cognitive": "recall",
    "cmd": "complete",
    "stem": [
      {
        "type": "text",
        "content": "\\StemText{\nThe length, $s$ metres, of a ship is 287 m, correct to the nearest metre.\n\\newline\n}\n\n\\StemText{\nComplete this statement about the value of $s$.\n\\newline\n}"
      }
    ],
    "answer": {
      "type": "number",
      "prefix": "~~~~~~~~",
      "suffix": " $\\le s < $ "
    },
    "_rawBody": "\\StemText{\nThe length, $s$ metres, of a ship is 287 m, correct to the nearest metre.\n}\n\n\\StemText{\nComplete this statement about the value of $s$.\n}\n\n\\AnswerLine[~~~~~~~~][ $\\le s < $ ]\n\\Marks{2}",
    "_compactMarks": true
  },
  {
    "id": "0580-2023OctNov-Paper11-Q23",
    "paper": "2023OctNov-Paper11",
    "qnum": 23,
    "marks": 1,
    "topics": [
      "Probability",
      "Statistics"
    ],
    "s": "8.1",
    "d": 1,
    "cat": "probability",
    "topic": "Basic probability",
    "qtype": "basic probability",
    "g": "mixed",
    "src": "0580/11/O/N/23 Q23",
    "year": 2023,
    "session": "OctNov",
    "tex": "The table shows the number of people in a town who are left-handed and the number who are right-handed.\n\\newline\n}\n\n\\begin{tabular}{|l|c|c|c|}\n\\hline\n& **Left-handed** & **Right-handed** & **Total** \\\\\n\\hline\n**Number of people** & $8\\,400$ & $48\\,600$ & $57\\,000$ \\\\\n\\hline\n\\end{tabular}\n\nWrite down the probability that a person, chosen at random, is left-handed.\n\\newline\n",
    "parts": [],
    "hasFigure": true,
    "cognitive": "recall",
    "cmd": "write",
    "stem": [
      {
        "type": "text",
        "content": "\\StemText{\nThe table shows the number of people in a town who are left-handed and the number who are right-handed.\n\\newline\n}"
      },
      {
        "type": "table",
        "content": "\\begin{center}\n\\begin{tabular}{|l|c|c|c|}\n\\hline\n& \\textbf{Left-handed} & \\textbf{Right-handed} & \\textbf{Total} \\\\\n\\hline\n\\textbf{Number of people} & 8\\,400 & 48\\,600 & 57\\,000 \\\\\n\\hline\n\\end{tabular}\n\\end{center}"
      },
      {
        "type": "text",
        "content": "\\StemText{\nWrite down the probability that a person, chosen at random, is left-handed.\n\\newline\n}"
      },
      {
        "type": "figure",
        "src": "https://git25math.github.io/25maths-cie0580-figures/2023OctNov/Paper11/Q23/Q23.png"
      }
    ],
    "answer": {
      "type": "number"
    },
    "_rawBody": "\\StemText{\nThe table shows the number of people in a town who are left-handed and the number who are right-handed.\n}\n\n\\begin{center}\n\\begin{tabular}{|l|c|c|c|}\n\\hline\n& \\textbf{Left-handed} & \\textbf{Right-handed} & \\textbf{Total} \\\\\n\\hline\n\\textbf{Number of people} & 8\\,400 & 48\\,600 & 57\\,000 \\\\\n\\hline\n\\end{tabular}\n\\end{center}\n\n\\StemText{\nWrite down the probability that a person, chosen at random, is left-handed.\n}\n\n\\AnswerLine[][]\n\\Marks{1}",
    "_compactMarks": true,
    "figureUrls": [
      "https://git25math.github.io/25maths-cie0580-figures/2023OctNov/Paper11/Q23/Q23.png"
    ]
  },
  {
    "id": "0580-2023OctNov-Paper11-Q24",
    "paper": "2023OctNov-Paper11",
    "qnum": 24,
    "marks": 24,
    "topics": [
      "Statistics"
    ],
    "s": "9.3",
    "d": 1,
    "cat": "statistics",
    "topic": "Frequency tables",
    "qtype": "averages and spread",
    "g": "mixed",
    "src": "0580/11/O/N/23 Q24",
    "year": 2023,
    "session": "OctNov",
    "tex": "(a) Change 1.2 m$^2$ into mm$^2$.\n\\newline\n\n(b) The speed limit on a road is 80 km/h.\n\\newline\n\\\\\nSophie drives at a speed of 1200 m/min.\n\\newline\n\nShow that Sophie drives at a speed lower than the speed limit.\n\\newline\n",
    "parts": [
      {
        "label": "(a)",
        "marks": 1,
        "content": [
          {
            "type": "text",
            "content": "Change 1.2 m$^2$ into mm$^2$.\n\\newline\n"
          }
        ],
        "answer": {
          "type": "number",
          "suffix": "mm$^2$"
        },
        "_compactMarks": true
      },
      {
        "label": "(b)",
        "marks": 2,
        "content": [
          {
            "type": "text",
            "content": "The speed limit on a road is 80 km/h.\n\\newline\n\\\\\nSophie drives at a speed of 1200 m/min.\n\\newline\n\n\\StemText{\nShow that Sophie drives at a speed lower than the speed limit.\n\\newline\n}"
          }
        ],
        "answer": {
          "type": "none",
          "space": {
            "type": "drawing",
            "height": "2cm",
            "cmd": "Answerspace"
          }
        },
        "_compactMarks": true
      }
    ],
    "hasFigure": false,
    "cognitive": "analyse",
    "cmd": "show",
    "stem": [],
    "_rawBody": "\\begin{parts}\n\\item Change 1.2 m$^2$ into mm$^2$.\n\n\\AnswerLine[][mm$^2$]\n\\Marks{1}\n\n\\item The speed limit on a road is 80 km/h.\\\\\nSophie drives at a speed of 1200 m/min.\n\n\\StemText{\nShow that Sophie drives at a speed lower than the speed limit.\n}\n\n\\Answerspace[2cm]\n\\Marks{2}\n\n\\end{parts}",
    "_compactParts": true,
    "_compactBegin": true
  },
  {
    "id": "0580-2023OctNov-Paper11-Q25",
    "paper": "2023OctNov-Paper11",
    "qnum": 25,
    "marks": 2,
    "topics": [
      "Geometry",
      "Mensuration",
      "Statistics"
    ],
    "s": "4.6",
    "d": 1,
    "cat": "geometry",
    "topic": "Constructions",
    "qtype": "angle calculations",
    "g": "mixed",
    "src": "0580/11/O/N/23 Q25",
    "year": 2023,
    "session": "OctNov",
    "tex": "Calculate the area of a semicircle with radius 10 cm.\n\\newline\n",
    "parts": [],
    "hasFigure": false,
    "cognitive": "apply",
    "cmd": "calculate",
    "stem": [
      {
        "type": "text",
        "content": "\\StemText{\nCalculate the area of a semicircle with radius 10 cm.\n\\newline\n}"
      }
    ],
    "answer": {
      "type": "number",
      "suffix": "cm$^2$"
    },
    "_rawBody": "\\StemText{\nCalculate the area of a semicircle with radius 10 cm.\n}\n\n\\AnswerLine[][cm$^2$]\n\\Marks{2}",
    "_compactMarks": true
  }
]